Workbook

Sheet BD
A1: EIXO | B1: ITEM | C1: Art | D1: REQUISITO | E1: Descrição | F1: Ponto Aplicáveis 2026 | G1: Pontos Recebidos 2026 | H1: Performance | I1: Responsável CEIInGov | J1: Coordenador Executivo | K1: Setor Executor | L1: Passível de Esforço Externo | M1: Dados/Sistema | N1: PERÍODO DE REFERÊNCIA | O1: DEADLINE | P1: OBSERVAÇÃO | Q1: Pontos Recebidos 2025 | R1: Pontos Recebidos 2024 | S1: Itens de Medição Parcial GEDAD | T1: FORMULÁRIO | U1: PONTOS APLICÁVEIS | V1: PONTOS ESTIMADOS
A2: 1. GOVERNANÇA | B2: Resolução CNJ nº 219/2016 (priorização do 1º Grau) | C2: 9.I.A | D2: Funções Comissionadas entre 1º e 2º graus | E2: Distribuição dos(as) servidores(as) entre os graus de jurisdição | F2: 20 | G2: =V2 -> 0 | H2: =IFERROR(G2/F2,0) -> 0 | I2: Meales Medeiros de Melo | J2: Fabio Jose de Oliveira Araujo | K2: GEDAD | M2: SRH | N2: SITUAÇÃO EM 30/06/2026 | O2: 46203 | Q2: 20 | R2: 10 | S2: x | T2: =IF(D2=B2,CONCATENATE(A2," - ",B2),CONCATENATE(A2," - ",B2," - ",D2)) -> 1. GOVERNANÇA - Resolução CNJ nº 219/2016 (priorização do 1º Grau) - Funções Comissionadas entre 1º e 2º graus | U2: =F2 -> 20 | V2: =IFERROR(VLOOKUP(T2,'Parcial - Prestação de contas'!A:D,4, ),0) -> 0
A3: 1. GOVERNANÇA | B3: Resolução CNJ nº 219/2016 (priorização do 1º Grau) | C3: 9.I.B | D3: Cargos em Comissão entre 1º e 2º graus | E3: Distribuição dos valores integrais das funções comissionadas entre os graus de jurisdição | F3: 20 | G3: =V3 -> 0 | H3: =IFERROR(G3/F3,0) -> 0 | I3: Meales Medeiros de Melo | J3: Fabio Jose de Oliveira Araujo | K3: GEDAD | M3: SRH | N3: SITUAÇÃO EM 30/06/2026 | O3: 46203 | Q3: 20 | R3: 10 | S3: x | T3: =IF(D3=B3,CONCATENATE(A3," - ",B3),CONCATENATE(A3," - ",B3," - ",D3)) -> 1. GOVERNANÇA - Resolução CNJ nº 219/2016 (priorização do 1º Grau) - Cargos em Comissão entre 1º e 2º graus | U3: =F3 -> 20 | V3: =IFERROR(VLOOKUP(T3,'Parcial - Prestação de contas'!A:D,4, ),0) -> 0
A4: 1. GOVERNANÇA | B4: Resolução CNJ nº 219/2016 (priorização do 1º Grau) | C4: 9.I.C | D4: Quantidade de servidores entre 1º e 2º graus | E4: Distribuição dos valores integrais dos cargos em comissão entre os graus de jurisdição | F4: 20 | G4: =V4 -> 0 | H4: =IFERROR(G4/F4,0) -> 0 | I4: Meales Medeiros de Melo | J4: Fabio Jose de Oliveira Araujo | K4: GEDAD | M4: SRH | N4: SITUAÇÃO EM 30/06/2026 | O4: 46203 | Q4: 0 | R4: 0 | S4: x | T4: =IF(D4=B4,CONCATENATE(A4," - ",B4),CONCATENATE(A4," - ",B4," - ",D4)) -> 1. GOVERNANÇA - Resolução CNJ nº 219/2016 (priorização do 1º Grau) - Quantidade de servidores entre 1º e 2º graus | U4: =F4 -> 20 | V4: =IFERROR(VLOOKUP(T4,'Parcial - Prestação de contas'!A:D,4, ),0) -> 0
A5: 1. GOVERNANÇA | B5: Resolução CNJ nº 219/2016 (priorização do 1º Grau) | C5: 9.I.D | D5: Cargos em comissão da área administrativa | E5: Limite de 30,00% na área de apoio indireto – servidores(as) | F5: 5 | G5: =V5 -> 0 | H5: =IFERROR(G5/F5,0) -> 0 | I5: Meales Medeiros de Melo | J5: Fabio Jose de Oliveira Araujo | K5: GEDAD | M5: SRH | N5: SITUAÇÃO EM 30/06/2026 | O5: 46203 | Q5: 5 | R5: 5 | S5: x | T5: =IF(D5=B5,CONCATENATE(A5," - ",B5),CONCATENATE(A5," - ",B5," - ",D5)) -> 1. GOVERNANÇA - Resolução CNJ nº 219/2016 (priorização do 1º Grau) - Cargos em comissão da área administrativa | U5: =F5 -> 5 | V5: =IFERROR(VLOOKUP(T5,'Parcial - Prestação de contas'!A:D,4, ),0) -> 0
A6: 1. GOVERNANÇA | B6: Resolução CNJ nº 219/2016 (priorização do 1º Grau) | C6: 9.I.E | D6: Funções comissionadas da área administrativa | E6: Limite de 30,00% na área de apoio indireto – funções comissionadas | F6: 5 | G6: =V6 -> 0 | H6: =IFERROR(G6/F6,0) -> 0 | I6: Meales Medeiros de Melo | J6: Fabio Jose de Oliveira Araujo | K6: GEDAD | M6: SRH | N6: SITUAÇÃO EM 30/06/2026 | O6: 46203 | Q6: 5 | R6: 5 | S6: x | T6: =IF(D6=B6,CONCATENATE(A6," - ",B6),CONCATENATE(A6," - ",B6," - ",D6)) -> 1. GOVERNANÇA - Resolução CNJ nº 219/2016 (priorização do 1º Grau) - Funções comissionadas da área administrativa | U6: =F6 -> 5 | V6: =IFERROR(VLOOKUP(T6,'Parcial - Prestação de contas'!A:D,4, ),0) -> 0
A7: 1. GOVERNANÇA | B7: Resolução CNJ nº 219/2016 (priorização do 1º Grau) | C7: 9.I.F | D7: Quantidade de servidores da área administrativa | E7: Limite de 30,00% na área de apoio indireto – cargos em comissão | F7: 5 | G7: =V7 -> 0 | H7: =IFERROR(G7/F7,0) -> 0 | I7: Meales Medeiros de Melo | J7: Fabio Jose de Oliveira Araujo | K7: GEDAD | M7: SRH | N7: SITUAÇÃO EM 30/06/2026 | O7: 46203 | Q7: 5 | R7: 5 | S7: x | T7: =IF(D7=B7,CONCATENATE(A7," - ",B7),CONCATENATE(A7," - ",B7," - ",D7)) -> 1. GOVERNANÇA - Resolução CNJ nº 219/2016 (priorização do 1º Grau) - Quantidade de servidores da área administrativa | U7: =F7 -> 5 | V7: =IFERROR(VLOOKUP(T7,'Parcial - Prestação de contas'!A:D,4, ),0) -> 0
A8: 1. GOVERNANÇA | B8: Resolução CNJ nº 219/2016 (priorização do 1º Grau) | C8: 9.I.G | D8: Orçamento entre 1º e 2º graus | E8: Distribuição do orçamento de natureza não vinculada entre os graus de jurisdição, proporcional à média de casos novos do triênio | F8: 10 | G8: =V8 -> 0 | H8: =IFERROR(G8/F8,0) -> 0 | I8: Meales Medeiros de Melo | J8: Leonardo Sousa de Paiva Oliveira | K8: DIFIN | N8: Lei Orçamentária Anual (LOA) de 2026 | O8: 46022 | Q8: 10 | R8: 10 | T8: =IF(D8=B8,CONCATENATE(A8," - ",B8),CONCATENATE(A8," - ",B8," - ",D8)) -> 1. GOVERNANÇA - Resolução CNJ nº 219/2016 (priorização do 1º Grau) - Orçamento entre 1º e 2º graus | U8: =F8 -> 10 | V8: =IFERROR(VLOOKUP(T8,'Parcial - Prestação de contas'!A:D,4, ),0) -> 0
A9: 1. GOVERNANÇA | B9: Gestão participativa na elaboração das Metas Nacionais | C9: 9.II.A1 | D9: Realizar audiência pública | E9: Realizar consulta pública | F9: 15 | G9: =V9 -> 0 | H9: =IFERROR(G9/F9,0) -> 0 | I9: Meales Medeiros de Melo | J9: Antonieta Lucia Maroja Arcoverde Nobrega | K9: GEPLA | M9: PLANILHA | N9: 01/01/2026 A 31/07/2026 | O9: 46234 | Q9: 15 | R9: 15 | T9: =IF(D9=B9,CONCATENATE(A9," - ",B9),CONCATENATE(A9," - ",B9," - ",D9)) -> 1. GOVERNANÇA - Gestão participativa na elaboração das Metas Nacionais - Realizar audiência pública | U9: =F9 -> 15 | V9: =IFERROR(VLOOKUP(T9,'Parcial - Prestação de contas'!A:D,4, ),0) -> 0
A10: 1. GOVERNANÇA | B10: Gestão participativa na elaboração das Metas Nacionais | C10: 9.II.A2 | D10: Realizar consulta pública | E10: Realizar audiência pública | F10: 15 | G10: =V10 -> 0 | H10: =IFERROR(G10/F10,0) -> 0 | I10: Meales Medeiros de Melo | J10: Antonieta Lucia Maroja Arcoverde Nobrega | K10: GEPLA | M10: PLANILHA | N10: 01/01/2026 A 31/07/2026 | O10: 46234 | Q10: 15 | R10: 0 | T10: =IF(D10=B10,CONCATENATE(A10," - ",B10),CONCATENATE(A10," - ",B10," - ",D10)) -> 1. GOVERNANÇA - Gestão participativa na elaboração das Metas Nacionais - Realizar consulta pública | U10: =F10 -> 15 | V10: =IFERROR(VLOOKUP(T10,'Parcial - Prestação de contas'!A:D,4, ),0) -> 0
A11: 1. GOVERNANÇA | B11: Gestão participativa na elaboração das Metas Nacionais | C11: 9.II.B | D11: Realizar uma ou mais reuniões com Magistrados e servidores | E11: Realizar uma ou mais reuniões com Magistrados e servidores | F11: 30 | G11: =V11 -> 0 | H11: =IFERROR(G11/F11,0) -> 0 | I11: Meales Medeiros de Melo | J11: Antonieta Lucia Maroja Arcoverde Nobrega | K11: GEPLA | M11: PLANILHA | N11: 01/01/2026 A 31/07/2026 | O11: 46234 | Q11: 30 | R11: 30 | T11: =IF(D11=B11,CONCATENATE(A11," - ",B11),CONCATENATE(A11," - ",B11," - ",D11)) -> 1. GOVERNANÇA - Gestão participativa na elaboração das Metas Nacionais - Realizar uma ou mais reuniões com Magistrados e servidores | U11: =F11 -> 30 | V11: =IFERROR(VLOOKUP(T11,'Parcial - Prestação de contas'!A:D,4, ),0) -> 0
A12: 1. GOVERNANÇA | B12: Gestão Socioambiental e IDS | C12: 9.III | D12: Resultado do IDS | E12: Resultado do IDS | F12: 50 | G12: =V12 -> 0 | H12: =IFERROR(G12/F12,0) -> 0 | I12: Meales Medeiros de Melo | J12: Lua Yamaoka Mariz Maia Pitanga | K12: NGSA | M12: PLANILHA | N12: ANO-BASE 2025 | O12: 46022 | Q12: 20 | R12: 15 | T12: =IF(D12=B12,CONCATENATE(A12," - ",B12),CONCATENATE(A12," - ",B12," - ",D12)) -> 1. GOVERNANÇA - Gestão Socioambiental e IDS - Resultado do IDS | U12: =F12 -> 50 | V12: =IFERROR(VLOOKUP(T12,'Parcial - Prestação de contas'!A:D,4, ),0) -> 0
A13: 1. GOVERNANÇA | B13: Judicialização da Saúde | C13: 9.IV.A | D13: Possuir NatJus | E13: Possuir NatJus que realize apoio técnico nas ações de saúde suplementar | F13: 10 | G13: =V13 -> 0 | H13: =IFERROR(G13/F13,0) -> 0 | I13: Meales Medeiros de Melo | J13: Silmary Alves de Queiroga Vita | K13: COMITÊ ESTADUAL DE SAÚDE | M13: PLANILHA | N13: SITUAÇÃO EM 31/07/2026 | O13: 46234 | Q13: 10 | R13: 10 | T13: =IF(D13=B13,CONCATENATE(A13," - ",B13),CONCATENATE(A13," - ",B13," - ",D13)) -> 1. GOVERNANÇA - Judicialização da Saúde - Possuir NatJus | U13: =F13 -> 10 | V13: =IFERROR(VLOOKUP(T13,'Parcial - Prestação de contas'!A:D,4, ),0) -> 0
A14: 1. GOVERNANÇA | B14: Judicialização da Saúde | C14: 9.IV.B | D14: Executar Plano de Estadual | E14: Executar duas ações do Plano Estadual ou Distrital elaborado | F14: 10 | G14: =V14 -> 0 | H14: =IFERROR(G14/F14,0) -> 0 | I14: Meales Medeiros de Melo | J14: Silmary Alves de Queiroga Vita | K14: COMITÊ ESTADUAL DE SAÚDE | M14: PLANILHA | N14: 01/08/2025 A 31/07/2026 | O14: 46234 | Q14: 10 | T14: =IF(D14=B14,CONCATENATE(A14," - ",B14),CONCATENATE(A14," - ",B14," - ",D14)) -> 1. GOVERNANÇA - Judicialização da Saúde - Executar Plano de Estadual | U14: =F14 -> 10 | V14: =IFERROR(VLOOKUP(T14,'Parcial - Prestação de contas'!A:D,4, ),0) -> 0
A15: 1. GOVERNANÇA | B15: Judicialização da Saúde | C15: 9.IV.C | D15: Acordo de Cooperação Técnica | E15: Possuir acordo de cooperação técnica, ou instrumento similar, com entes do SUS ou com operadoras de planos de saúde | F15: 10 | G15: =V15 -> 0 | H15: =IFERROR(G15/F15,0) -> 0 | I15: Meales Medeiros de Melo | J15: Silmary Alves de Queiroga Vita | K15: COMITÊ ESTADUAL DE SAÚDE | M15: PLANILHA | N15: SITUAÇÃO EM 31/07/2026 | O15: 46234 | Q15: 10 | R15: 10 | T15: =IF(D15=B15,CONCATENATE(A15," - ",B15),CONCATENATE(A15," - ",B15," - ",D15)) -> 1. GOVERNANÇA - Judicialização da Saúde - Acordo de Cooperação Técnica | U15: =F15 -> 10 | V15: =IFERROR(VLOOKUP(T15,'Parcial - Prestação de contas'!A:D,4, ),0) -> 0
A16: 1. GOVERNANÇA | B16: Judicialização da Saúde | C16: 9.IV.D | D16: Capacitação | E16: Realizar cursos capacitação com os(as) magistrados(as), voltados ao Direito da Saúde e/ou Judicialização da Saúde | F16: 10 | G16: =V16 -> 0 | H16: =IFERROR(G16/F16,0) -> 0 | I16: Meales Medeiros de Melo | J16: Silmary Alves de Queiroga Vita | K16: ESMA | M16: PLANILHA | N16: 01/08/2025 A 31/07/2026 | O16: 46234 | Q16: 10 | T16: =IF(D16=B16,CONCATENATE(A16," - ",B16),CONCATENATE(A16," - ",B16," - ",D16)) -> 1. GOVERNANÇA - Judicialização da Saúde - Capacitação | U16: =F16 -> 10 | V16: =IFERROR(VLOOKUP(T16,'Parcial - Prestação de contas'!A:D,4, ),0) -> 0
A17: 1. GOVERNANÇA | B17: Judicialização da Saúde | C17: 9.IV.E | D17: Possuir unidade judiciária especializada na temática da saúde | E17: Possuir unidade judiciária especializada na temática da saúde | F17: 10 | G17: =V17 -> 0 | H17: =IFERROR(G17/F17,0) -> 0 | I17: Meales Medeiros de Melo | J17: Silmary Alves de Queiroga Vita | K17: GEDAD | M17: PLANILHA | N17: SITUAÇÃO EM 31/07/2026 | O17: 46234 | Q17: 10 | R17: 10 | T17: =IF(D17=B17,CONCATENATE(A17," - ",B17),CONCATENATE(A17," - ",B17," - ",D17)) -> 1. GOVERNANÇA - Judicialização da Saúde - Possuir unidade judiciária especializada na temática da saúde | U17: =F17 -> 10 | V17: =IFERROR(VLOOKUP(T17,'Parcial - Prestação de contas'!A:D,4, ),0) -> 0
A18: 1. GOVERNANÇA | B18: Centro de Inteligência do Poder Judiciário | C18: 9.V | D18: Emitir 3 Notas técnicas | E18: Emitir 3 Notas técnicas | F18: 15 | G18: =V18 -> 0 | H18: =IFERROR(G18/F18,0) -> 0 | I18: Meales Medeiros de Melo | J18: Jeremias de Cassio Carneiro de Melo | K18: GEPLA | M18: PLANILHA | N18: 01/08/2025 A 31/07/2026 | O18: 46234 | Q18: 15 | R18: 15 | T18: =IF(D18=B18,CONCATENATE(A18," - ",B18),CONCATENATE(A18," - ",B18," - ",D18)) -> 1. GOVERNANÇA - Centro de Inteligência do Poder Judiciário - Emitir 3 Notas técnicas | U18: =F18 -> 15 | V18: =IFERROR(VLOOKUP(T18,'Parcial - Prestação de contas'!A:D,4, ),0) -> 0
A19: 1. GOVERNANÇA | B19: Assédio Moral, Sexual e Discriminação | C19: 9.VI.A | D19: Capacitação de servidores chefes | E19: Realizar campanha de orientação e esclarecimento sobre assédio moral, assédio sexual e discriminação | F19: 10 | G19: =V19 -> 0 | H19: =IFERROR(G19/F19,0) -> 0 | I19: Meales Medeiros de Melo | J19: Tulia Gomes de Souza Neves | K19: COAPO | M19: PLANILHA | N19: 01/08/2025 A 31/07/2026 | O19: 46234 | Q19: 10 | R19: 10 | T19: =IF(D19=B19,CONCATENATE(A19," - ",B19),CONCATENATE(A19," - ",B19," - ",D19)) -> 1. GOVERNANÇA - Assédio Moral, Sexual e Discriminação - Capacitação de servidores chefes | U19: =F19 -> 10 | V19: =IFERROR(VLOOKUP(T19,'Parcial - Prestação de contas'!A:D,4, ),0) -> 0
A20: 1. GOVERNANÇA | B20: Assédio Moral, Sexual e Discriminação | C20: 9.VI.B | D20: Semana de Combate ao Assédio | E20: Possuir o mínimo de 20,00% dos(as) servidores(as) ocupantes de cargo de chefia do órgão capacitados na temática | F20: 10 | G20: =V20 -> 0 | H20: =IFERROR(G20/F20,0) -> 0 | I20: Meales Medeiros de Melo | J20: Tulia Gomes de Souza Neves | K20: ESMA | M20: PLANILHA | N20: 01/01/2022 A 31/07/2026 | O20: 46234 | Q20: 10 | T20: =IF(D20=B20,CONCATENATE(A20," - ",B20),CONCATENATE(A20," - ",B20," - ",D20)) -> 1. GOVERNANÇA - Assédio Moral, Sexual e Discriminação - Semana de Combate ao Assédio | U20: =F20 -> 10 | V20: =IFERROR(VLOOKUP(T20,'Parcial - Prestação de contas'!A:D,4, ),0) -> 0
A21: 1. GOVERNANÇA | B21: Assédio Moral, Sexual e Discriminação | C21: 9.VI.C | D21: Campanha de orientação | E21: Realizar a semana de combate ao assédio no mês de maio(magistrados(as), servidores(as) e quadro auxiliar) (10 pontos); | F21: 10 | G21: =V21 -> 0 | H21: =IFERROR(G21/F21,0) -> 0 | I21: Meales Medeiros de Melo | J21: Tulia Gomes de Souza Neves | K21: COAPO | M21: PLANILHA | N21: MAIO DE 2026 | O21: 46173 | Q21: 10 | R21: 10 | T21: =IF(D21=B21,CONCATENATE(A21," - ",B21),CONCATENATE(A21," - ",B21," - ",D21)) -> 1. GOVERNANÇA - Assédio Moral, Sexual e Discriminação - Campanha de orientação | U21: =F21 -> 10 | V21: =IFERROR(VLOOKUP(T21,'Parcial - Prestação de contas'!A:D,4, ),0) -> 0
A22: 1. GOVERNANÇA | B22: Assédio Moral, Sexual e Discriminação | C22: 9.VI.D | D22: Penquisa que avalie assédio no tribunal | E22: Ter realizado pelo menos uma pesquisa interna que avalie o assédio no tribunal | F22: 10 | G22: =V22 -> 0 | H22: =IFERROR(G22/F22,0) -> 0 | I22: Meales Medeiros de Melo | J22: Tulia Gomes de Souza Neves | K22: COAPO | M22: PLANILHA | N22: 01/01/2023 A 31/07/2026 | O22: 46234 | Q22: 10 | T22: =IF(D22=B22,CONCATENATE(A22," - ",B22),CONCATENATE(A22," - ",B22," - ",D22)) -> 1. GOVERNANÇA - Assédio Moral, Sexual e Discriminação - Penquisa que avalie assédio no tribunal | U22: =F22 -> 10 | V22: =IFERROR(VLOOKUP(T22,'Parcial - Prestação de contas'!A:D,4, ),0) -> 0
A23: 1. GOVERNANÇA | B23: Gestão de Memória e Documental | C23: 9.VII.A | D23: Ambientes físicos e virtuais de preservação da memória | E23: Publicação de pelo menos dois editais de eliminação | F23: 20 | G23: =V23 -> 0 | H23: =IFERROR(G23/F23,0) -> 0 | I23: Meales Medeiros de Melo | J23: Fabio Jose de Oliveira Araujo | K23: CPAD | M23: PLANILHA | N23: 01/08/2025 A 31/07/2026 | O23: 46234 | Q23: 20 | R23: 20 | T23: =IF(D23=B23,CONCATENATE(A23," - ",B23),CONCATENATE(A23," - ",B23," - ",D23)) -> 1. GOVERNANÇA - Gestão de Memória e Documental - Ambientes físicos e virtuais de preservação da memória | U23: =F23 -> 20 | V23: =IFERROR(VLOOKUP(T23,'Parcial - Prestação de contas'!A:D,4, ),0) -> 0
A24: 1. GOVERNANÇA | B24: Gestão de Memória e Documental | C24: 9.VII.B | D24: Editais de eliminação | E24: Possuir ambientes físicos e virtuais de preservação da memória | F24: 10 | G24: =V24 -> 0 | H24: =IFERROR(G24/F24,0) -> 0 | I24: Meales Medeiros de Melo | J24: Fabio Jose de Oliveira Araujo | K24: CPAD | M24: PLANILHA | N24: SITUAÇÃO EM 31/07/2026 | O24: 46234 | Q24: 10 | R24: 10 | T24: =IF(D24=B24,CONCATENATE(A24," - ",B24),CONCATENATE(A24," - ",B24," - ",D24)) -> 1. GOVERNANÇA - Gestão de Memória e Documental - Editais de eliminação | U24: =F24 -> 10 | V24: =IFERROR(VLOOKUP(T24,'Parcial - Prestação de contas'!A:D,4, ),0) -> 0
A25: 1. GOVERNANÇA | B25: Política Nacional de Justiça Restaurativa | C25: 9.VIII.A | D25: Possuir CEJURE | E25: Possuir pelo menos um Núcleo de Justiça Restaurativa estruturado que contenha, no mínimo, dois servidores(as) com dedicação exclusiva e capacitados(as) como facilitadores(as) em práticas restaurativas | F25: 10 | G25: =V25 -> 0 | H25: =IFERROR(G25/F25,0) -> 0 | I25: Meales Medeiros de Melo | J25: Ivna Mozart Bezerra Soares | K25: NEJURE | M25: PLANILHA | N25: SITUAÇÃO EM 31/07/2026 | O25: 46234 | Q25: 10 | R25: 10 | T25: =IF(D25=B25,CONCATENATE(A25," - ",B25),CONCATENATE(A25," - ",B25," - ",D25)) -> 1. GOVERNANÇA - Política Nacional de Justiça Restaurativa - Possuir CEJURE | U25: =F25 -> 10 | V25: =IFERROR(VLOOKUP(T25,'Parcial - Prestação de contas'!A:D,4, ),0) -> 0
A26: 1. GOVERNANÇA | B26: Política Nacional de Justiça Restaurativa | C26: 9.VIII.B | D26: Capacitação | E26: Realizar capacitação, na teoria e prática da Justiça Restaurativa, nos termos do Plano Pedagógico Mínimo Orientador para Formações em Justiça Restaurativa | F26: 20 | G26: =V26 -> 0 | H26: =IFERROR(G26/F26,0) -> 0 | I26: Meales Medeiros de Melo | J26: Ivna Mozart Bezerra Soares | K26: NEJURE | M26: PLANILHA | N26: 01/08/2025 A 31/07/2026 | O26: 46234 | Q26: 20 | R26: 20 | T26: =IF(D26=B26,CONCATENATE(A26," - ",B26),CONCATENATE(A26," - ",B26," - ",D26)) -> 1. GOVERNANÇA - Política Nacional de Justiça Restaurativa - Capacitação | U26: =F26 -> 20 | V26: =IFERROR(VLOOKUP(T26,'Parcial - Prestação de contas'!A:D,4, ),0) -> 0
A27: 1. GOVERNANÇA | B27: Política Nacional de Justiça Restaurativa | C27: 9.VIII.C | D27: Relatório de Atividades | E27: Relatório de atividades do Núcleo de Justiça Restaurativa | F27: 10 | G27: =V27 -> 0 | H27: =IFERROR(G27/F27,0) -> 0 | I27: Meales Medeiros de Melo | J27: Ivna Mozart Bezerra Soares | K27: NEJURE | M27: PLANILHA | N27: 01/08/2025 A 31/07/2026 | O27: 46234 | Q27: 10 | R27: 10 | T27: =IF(D27=B27,CONCATENATE(A27," - ",B27),CONCATENATE(A27," - ",B27," - ",D27)) -> 1. GOVERNANÇA - Política Nacional de Justiça Restaurativa - Relatório de Atividades | U27: =F27 -> 10 | V27: =IFERROR(VLOOKUP(T27,'Parcial - Prestação de contas'!A:D,4, ),0) -> 0
A28: 1. GOVERNANÇA | B28: Instalar GMF | C28: 9.IX.A.EB | D28: Estrutura de apoio administrativo / Equipe multiprofissional | E28: Estrutura de apoio administrativo / Equipe multiprofissional | F28: 20 | G28: =V28 -> 0 | H28: =IFERROR(G28/F28,0) -> 0 | I28: Meales Medeiros de Melo | J28: Maria Aparecida Sarmento Gadelha | K28: GMF | M28: PLANILHA | N28: SITUAÇÃO EM 31/07/2026 | O28: 46234 | Q28: 20 | R28: 20 | T28: =IF(D28=B28,CONCATENATE(A28," - ",B28),CONCATENATE(A28," - ",B28," - ",D28)) -> 1. GOVERNANÇA - Instalar GMF - Estrutura de apoio administrativo / Equipe multiprofissional | U28: =F28 -> 20 | V28: =IFERROR(VLOOKUP(T28,'Parcial - Prestação de contas'!A:D,4, ),0) -> 0
A29: 1. GOVERNANÇA | B29: Inspeções nos estabelecimentos penais | C29: 9.X | D29: Inspeções nos estabelecimentos penais | E29: Inspeções nos estabelecimentos penais | F29: 30 | G29: =V29 -> 0 | H29: =IFERROR(G29/F29,0) -> 0 | I29: Meales Medeiros de Melo | J29: Maria Aparecida Sarmento Gadelha | K29: UNIDADES JUDICIÁRIAS | L29: X | M29: CNIEPS | N29: 01/09/2025 A 31/08/2026 | O29: 46265 | Q29: 0 | R29: 0 | S29: x | T29: =IF(D29=B29,CONCATENATE(A29," - ",B29),CONCATENATE(A29," - ",B29," - ",D29)) -> 1. GOVERNANÇA - Inspeções nos estabelecimentos penais | U29: =F29 -> 30 | V29: =IFERROR(VLOOKUP(T29,'Parcial - Prestação de contas'!A:D,4, ),0) -> 0
A30: 1. GOVERNANÇA | B30: Inspeções nos estabelecimentos de medidas socioeducativas | C30: 9.XI.A | D30: Meio Fechado | E30: Meio Fechado | F30: 20 | G30: =V30 -> 0 | H30: =IFERROR(G30/F30,0) -> 0 | I30: Meales Medeiros de Melo | J30: Antonieta Lucia Maroja Arcoverde Nobrega | K30: UNIDADES JUDICIÁRIAS | L30: X | M30: CNIUPS | N30: 01/07/2025 A 30/06/2026 | O30: 46203 | Q30: 20 | R30: 20 | S30: x | T30: =IF(D30=B30,CONCATENATE(A30," - ",B30),CONCATENATE(A30," - ",B30," - ",D30)) -> 1. GOVERNANÇA - Inspeções nos estabelecimentos de medidas socioeducativas - Meio Fechado | U30: =F30 -> 20 | V30: =IFERROR(VLOOKUP(T30,'Parcial - Prestação de contas'!A:D,4, ),0) -> 0
A31: 1. GOVERNANÇA | B31: Inspeções nos estabelecimentos de medidas socioeducativas | C31: 9.XI.B | D31: Meio aberto | E31: Meio aberto | F31: 10 | G31: =V31 -> 0 | H31: =IFERROR(G31/F31,0) -> 0 | I31: Meales Medeiros de Melo | J31: Antonieta Lucia Maroja Arcoverde Nobrega | K31: UNIDADES JUDICIÁRIAS | L31: X | M31: CNIUPS | N31: 01/07/2025 A 30/06/2026 | O31: 46203 | Q31: 10 | R31: 10 | S31: x | T31: =IF(D31=B31,CONCATENATE(A31," - ",B31),CONCATENATE(A31," - ",B31," - ",D31)) -> 1. GOVERNANÇA - Inspeções nos estabelecimentos de medidas socioeducativas - Meio aberto | U31: =F31 -> 10 | V31: =IFERROR(VLOOKUP(T31,'Parcial - Prestação de contas'!A:D,4, ),0) -> 0
A32: 1. GOVERNANÇA | B32: Participação Institucional Feminina | C32: 9.XII.A | D32: Paridade na promoção por merecimento | E32: Paridade de gênero nas promoções por merecimento do primeiro para o segundo grau; ou paridade no total de desembargadoras ativas e que tenham ingressado pelo critério de merecimento | F32: 10 | G32: =V32 -> 0 | H32: =IFERROR(G32/F32,0) -> 0 | I32: Meales Medeiros de Melo | J32: Maria Aparecida Sarmento Gadelha | K32: TRIBUNAL PLENO | M32: PLANILHA | N32: 01/08/2025 A 31/07/2026 | O32: 46234 | Q32: 10 | R32: 0 | T32: =IF(D32=B32,CONCATENATE(A32," - ",B32),CONCATENATE(A32," - ",B32," - ",D32)) -> 1. GOVERNANÇA - Participação Institucional Feminina - Paridade na promoção por merecimento | U32: =F32 -> 10 | V32: =IFERROR(VLOOKUP(T32,'Parcial - Prestação de contas'!A:D,4, ),0) -> 0
A33: 1. GOVERNANÇA | B33: Participação Institucional Feminina | C33: 9.XII.C | D33: Paridade magistradas auxiliares | E33: Percentual paritário de magistradas designadas como auxiliares para cargos na alta administração do Poder Judiciário (juíza auxiliar da presidência, vice-presidência e corregedoria; diretora de escolas judiciais; diretora de foro de seção judiciária; e ouvidora, inclusive ouvidora da mulher) | F33: 10 | G33: =V33 -> 0 | H33: =IFERROR(G33/F33,0) -> 0 | I33: Meales Medeiros de Melo | J33: Maria Aparecida Sarmento Gadelha | K33: PRESIDÊNCIA | M33: SRH | N33: SITUAÇÃO EM 31/07/2026 | O33: 46234 | Q33: 0 | R33: 0 | T33: =IF(D33=B33,CONCATENATE(A33," - ",B33),CONCATENATE(A33," - ",B33," - ",D33)) -> 1. GOVERNANÇA - Participação Institucional Feminina - Paridade magistradas auxiliares | U33: =F33 -> 10 | V33: =IFERROR(VLOOKUP(T33,'Parcial - Prestação de contas'!A:D,4, ),0) -> 0
A34: 1. GOVERNANÇA | B34: Participação Institucional Feminina | C34: 9.XII.D | D34: Paridade cortes eleitorais | E34: Percentual paritário de magistradas designadas para compor as cortes eleitorais | F34: 10 | G34: =V34 -> 0 | H34: =IFERROR(G34/F34,0) -> 0 | I34: Meales Medeiros de Melo | J34: Maria Aparecida Sarmento Gadelha | K34: TRIBUNAL PLENO | M34: PLANILHA | N34: 01/08/2025 A 31/07/2026 | O34: 46234 | Q34: 0 | R34: 10 | T34: =IF(D34=B34,CONCATENATE(A34," - ",B34),CONCATENATE(A34," - ",B34," - ",D34)) -> 1. GOVERNANÇA - Participação Institucional Feminina - Paridade cortes eleitorais | U34: =F34 -> 10 | V34: =IFERROR(VLOOKUP(T34,'Parcial - Prestação de contas'!A:D,4, ),0) -> 0
A35: 1. GOVERNANÇA | B35: Participação Institucional Feminina | C35: 9.XII.E | D35: Paridade servidoras ocupantes de cargos de chefia | E35: Percentual paritário de servidoras ocupantes de cargo de chefia | F35: 10 | G35: =V35 -> 0 | H35: =IFERROR(G35/F35,0) -> 0 | I35: Meales Medeiros de Melo | J35: Maria Aparecida Sarmento Gadelha | K35: GEDAD | M35: SRH | N35: SITUAÇÃO EM 31/07/2026 | O35: 46234 | Q35: 10 | R35: 10 | T35: =IF(D35=B35,CONCATENATE(A35," - ",B35),CONCATENATE(A35," - ",B35," - ",D35)) -> 1. GOVERNANÇA - Participação Institucional Feminina - Paridade servidoras ocupantes de cargos de chefia | U35: =F35 -> 10 | V35: =IFERROR(VLOOKUP(T35,'Parcial - Prestação de contas'!A:D,4, ),0) -> 0
A36: 1. GOVERNANÇA | B36: Apoio às Vítimas de Crimes e Atos Infracionais | C36: 9.XIII | D36: Centros Especializados de Atenção às Vítimas | E36: Existência de Centros Especializados de Atenção às Vítimas em funcionamento e estruturado com equipe multiprofissional. | F36: 20 | G36: =V36 -> 0 | H36: =IFERROR(G36/F36,0) -> 0 | I36: Meales Medeiros de Melo | J36: Maria Aparecida Sarmento Gadelha | K36: UNIDADES JUDICIÁRIAS | M36: PLANILHA | N36: 01/08/2025 A 31/07/2026 | O36: 46234 | Q36: 20 | R36: 20 | T36: =IF(D36=B36,CONCATENATE(A36," - ",B36),CONCATENATE(A36," - ",B36," - ",D36)) -> 1. GOVERNANÇA - Apoio às Vítimas de Crimes e Atos Infracionais - Centros Especializados de Atenção às Vítimas | U36: =F36 -> 20 | V36: =IFERROR(VLOOKUP(T36,'Parcial - Prestação de contas'!A:D,4, ),0) -> 0
A37: 1. GOVERNANÇA | B37: Acessibilidade e inclusão de pessoas com deficiência | C37: 9.XIV.A1 | D37: Eventos realizados | E37: Acessibilidade comunicacional: possuir 70,00% ou mais de eventos realizados com acessibilidade comunicacional, calculado pela relação (QEAc / QEt), conforme indicador 3.4 do anexo da referida resolução | F37: 10 | G37: =V37 -> 0 | H37: =IFERROR(G37/F37,0) -> 0 | I37: Meales Medeiros de Melo | J37: Fabio Jose de Oliveira Araujo | K37: CERIMONIAL/NGSA | M37: PLANILHA | N37: 01/01/2025 A 31/12/2025 | O37: 46022 | Q37: 10 | R37: 10 | T37: =IF(D37=B37,CONCATENATE(A37," - ",B37),CONCATENATE(A37," - ",B37," - ",D37)) -> 1. GOVERNANÇA - Acessibilidade e inclusão de pessoas com deficiência - Eventos realizados | U37: =F37 -> 10 | V37: =IFERROR(VLOOKUP(T37,'Parcial - Prestação de contas'!A:D,4, ),0) -> 0
A38: 1. GOVERNANÇA | B38: Acessibilidade e inclusão de pessoas com deficiência | C38: 9.XIV.A2 | D38: Recursos de tecnologia assistida para srvidores com deficiência visual | E38: Acessibilidade tecnológica: 5 pontos para cada recurso de tecnologia assistida que permita o uso de computadores por pessoas com deficiência visual - resolução | F38: 10 | G38: =V38 -> 0 | H38: =IFERROR(G38/F38,0) -> 0 | I38: Meales Medeiros de Melo | J38: Max Nunes de Franca | K38: DITEC | M38: PLANILHA | N38: ANO-BASE 2025 | O38: 46022 | Q38: 10 | R38: 10 | T38: =IF(D38=B38,CONCATENATE(A38," - ",B38),CONCATENATE(A38," - ",B38," - ",D38)) -> 1. GOVERNANÇA - Acessibilidade e inclusão de pessoas com deficiência - Recursos de tecnologia assistida para srvidores com deficiência visual | U38: =F38 -> 10 | V38: =IFERROR(VLOOKUP(T38,'Parcial - Prestação de contas'!A:D,4, ),0) -> 0
A39: 1. GOVERNANÇA | B39: Acessibilidade e inclusão de pessoas com deficiência | C39: 9.XIV.A.3.2 | D39: Servidores capacitados(as) | E39: Percentual de servidores(as) capacitados(as) nas temáticas de acessibilidade e inclusão das pessoas com deficiência igual ou maior que 10,00%, calculado pela relação: ((QS1 + QS2) / Serv) | F39: 5 | G39: =V39 -> 0 | H39: =IFERROR(G39/F39,0) -> 0 | I39: Meales Medeiros de Melo | J39: Antonieta Lucia Maroja Arcoverde Nobrega | K39: ESMA/NGSA | M39: PLANILHA | N39: ANO-BASE 2025 | O39: 46022 | Q39: 0 | R39: 0 | T39: =IF(D39=B39,CONCATENATE(A39," - ",B39),CONCATENATE(A39," - ",B39," - ",D39)) -> 1. GOVERNANÇA - Acessibilidade e inclusão de pessoas com deficiência - Servidores capacitados(as) | U39: =F39 -> 5 | V39: =IFERROR(VLOOKUP(T39,'Parcial - Prestação de contas'!A:D,4, ),0) -> 0
A40: 1. GOVERNANÇA | B40: Acessibilidade e inclusão de pessoas com deficiência | D40: Relatório de Ações da COMPACI | E40: Relatório de Ações da COMPACI que evidencie os seguintes temas: Acessibilidade Comunicacional, Acessibilidade tecnológica e Capacitação dos Servidores | G40: =V40 -> 0 | I40: Meales Medeiros de Melo | J40: Anna Carla Lopes Correia Lima de Freitas | K40: COAPO | M40: PLANILHA | N40: ANO-BASE 2025 | O40: 46022 | R40: 0 | T40: =IF(D40=B40,CONCATENATE(A40," - ",B40),CONCATENATE(A40," - ",B40," - ",D40)) -> 1. GOVERNANÇA - Acessibilidade e inclusão de pessoas com deficiência - Relatório de Ações da COMPACI | U40: =F40 | V40: =IFERROR(VLOOKUP(T40,'Parcial - Prestação de contas'!A:D,4, ),0) -> 0
A41: 1. GOVERNANÇA | B41: Acessibilidade e inclusão de pessoas com deficiência | C41: 9.XIV.A.3.3 | D41: Magistrados(as) capacitados(as) | E41: Percentual de magistrados(as) capacitados(as) nas temáticas de acessibilidade e inclusão das pessoas com deficiência igual ou maior que 10,00% | F41: 5 | G41: =V41 -> 0 | H41: =IFERROR(G41/F41,0) -> 0 | I41: Meales Medeiros de Melo | J41: Antonieta Lucia Maroja Arcoverde Nobrega | K41: ESMA | M41: PLANILHA | N41: 01/01/2024 a 31/07/2026 | O41: 46234 | Q41: 5 | R41: 5 | T41: =IF(D41=B41,CONCATENATE(A41," - ",B41),CONCATENATE(A41," - ",B41," - ",D41)) -> 1. GOVERNANÇA - Acessibilidade e inclusão de pessoas com deficiência - Magistrados(as) capacitados(as) | U41: =F41 -> 5 | V41: =IFERROR(VLOOKUP(T41,'Parcial - Prestação de contas'!A:D,4, ),0) -> 0
A42: 1. GOVERNANÇA | B42: Acessibilidade e inclusão de pessoas com deficiência | C42: 9.XIV.B | D42: Projeto de uso de linguagem simples | E42: Ter pelo menos um projeto de uso de linguagem simples com foco na prestação jurisdicional e/ou nos atos administrativos | F42: 10 | G42: =V42 -> 0 | H42: =IFERROR(G42/F42,0) -> 0 | I42: Meales Medeiros de Melo | J42: Natan Figueredo Oliveira | K42: GEPLA | M42: PLANILHA | N42: 01/08/2025 a 31/07/2026 | O42: 46234 | Q42: 10 | R42: 10 | T42: =IF(D42=B42,CONCATENATE(A42," - ",B42),CONCATENATE(A42," - ",B42," - ",D42)) -> 1. GOVERNANÇA - Acessibilidade e inclusão de pessoas com deficiência - Projeto de uso de linguagem simples | U42: =F42 -> 10 | V42: =IFERROR(VLOOKUP(T42,'Parcial - Prestação de contas'!A:D,4, ),0) -> 0
A43: 1. GOVERNANÇA | B43: Política de Gestão da Inovação | C43: 9.XV.A | D43: Laboratório de Inovação | E43: Ter implantado o Laboratório de Inovação, nos termos do art. 4º da Resolução CNJ nº 395/2021, e designado laboratoristas, dos quais ao menos um(a) magistrado(a) e um(a) servidor(a), este com dedicação exclusiva, e ambos com capacitação em gestão e operação de laboratórios de inovação de, no mínimo, 20h/aula | F43: 10 | G43: =V43 -> 0 | H43: =IFERROR(G43/F43,0) -> 0 | I43: Meales Medeiros de Melo | J43: Jeremias de Cassio Carneiro de Melo | K43: COINO | M43: PLANILHA | N43: SITUAÇÃO EM 31/07/2026 | O43: 46234 | Q43: 10 | R43: 10 | T43: =IF(D43=B43,CONCATENATE(A43," - ",B43),CONCATENATE(A43," - ",B43," - ",D43)) -> 1. GOVERNANÇA - Política de Gestão da Inovação - Laboratório de Inovação | U43: =F43 -> 10 | V43: =IFERROR(VLOOKUP(T43,'Parcial - Prestação de contas'!A:D,4, ),0) -> 0
A44: 1. GOVERNANÇA | B44: Política de Gestão da Inovação | C44: 9.XV.B | D44: Projeto design thinking | E44: Encaminhar relatório de iniciativa na qual tenha sido utilizada a abordagem do design thinking na fase de identificação/análise do problema e geração/seleção de alternativas de solução para prototipagem e teste, independentemente da metodologia utilizada na fase de gerenciamento do projeto decorrente | F44: 10 | G44: =V44 -> 0 | H44: =IFERROR(G44/F44,0) -> 0 | I44: Meales Medeiros de Melo | J44: Jeremias de Cassio Carneiro de Melo | K44: COINO | M44: PLANILHA | N44: 01/08/2025 a 31/07/2026 | O44: 46234 | Q44: 10 | R44: 10 | T44: =IF(D44=B44,CONCATENATE(A44," - ",B44),CONCATENATE(A44," - ",B44," - ",D44)) -> 1. GOVERNANÇA - Política de Gestão da Inovação - Projeto design thinking | U44: =F44 -> 10 | V44: =IFERROR(VLOOKUP(T44,'Parcial - Prestação de contas'!A:D,4, ),0) -> 0
A45: 1. GOVERNANÇA | B45: Núcleo de cooperação judiciária | C45: 9.XVI.A | D45: Iniciativa promovida pelo núcleo | E45: Realizar pelo menos uma iniciativa promovida pelo núcleo de cooperação judiciária, formalmente constituído | F45: 10 | G45: =V45 -> 0 | H45: =IFERROR(G45/F45,0) -> 0 | I45: Meales Medeiros de Melo | J45: Lua Yamaoka Mariz Maia Pitanga | K45: VICE | M45: PLANILHA | N45: 01/08/2025 a 31/07/2026 | O45: 46234 | Q45: 10 | R45: 10 | T45: =IF(D45=B45,CONCATENATE(A45," - ",B45),CONCATENATE(A45," - ",B45," - ",D45)) -> 1. GOVERNANÇA - Núcleo de cooperação judiciária - Iniciativa promovida pelo núcleo | U45: =F45 -> 10 | V45: =IFERROR(VLOOKUP(T45,'Parcial - Prestação de contas'!A:D,4, ),0) -> 0
A46: 1. GOVERNANÇA | B46: Núcleo de cooperação judiciária | C46: 9.XVI.B | D46: Iniciativa promovida pelo magistrado de cooperação | E46: Realizar pelo menos uma iniciativa promovida por magistrados(as) de cooperação judiciária | F46: 10 | G46: =V46 -> 0 | H46: =IFERROR(G46/F46,0) -> 0 | I46: Meales Medeiros de Melo | J46: Lua Yamaoka Mariz Maia Pitanga | K46: VICE | M46: PLANILHA | N46: 01/08/2025 a 31/07/2026 | O46: 46234 | Q46: 10 | R46: 10 | T46: =IF(D46=B46,CONCATENATE(A46," - ",B46),CONCATENATE(A46," - ",B46," - ",D46)) -> 1. GOVERNANÇA - Núcleo de cooperação judiciária - Iniciativa promovida pelo magistrado de cooperação | U46: =F46 -> 10 | V46: =IFERROR(VLOOKUP(T46,'Parcial - Prestação de contas'!A:D,4, ),0) -> 0
A47: 1. GOVERNANÇA | B47: Núcleo de cooperação judiciária | C47: 9.XVII.A | D47: Capacitação - Direitos Humanos | E47: Promoverem cursos de formação inicial e de formação continuada para capacitação magistrados(as) ativos(as), de primeiro e segundo graus de jurisdição, que incluam, obrigatoriamente, os conteúdos relativos aos direitos humanos, gênero, raça e etnia, bem como de servidores (as), os quais deverão ser disponibilizados com periodicidade mínima anual, preferencialmente na modalidade presencial ou híbrida | F47: 20 | G47: =V47 -> 0 | H47: =IFERROR(G47/F47,0) -> 0 | I47: Meales Medeiros de Melo | J47: Antonieta Lucia Maroja Arcoverde Nobrega | K47: ESMA | M47: PLANILHA | N47: 01/08/2025 a 31/07/2026 | O47: 46234 | Q47: 20 | R47: 20 | T47: =IF(D47=B47,CONCATENATE(A47," - ",B47),CONCATENATE(A47," - ",B47," - ",D47)) -> 1. GOVERNANÇA - Núcleo de cooperação judiciária - Capacitação - Direitos Humanos | U47: =F47 -> 20 | V47: =IFERROR(VLOOKUP(T47,'Parcial - Prestação de contas'!A:D,4, ),0) -> 0
A48: 1. GOVERNANÇA | B48: Capacitação de Magistrados e servidores | C48: 9.XVII.B | D48: Capacitação - Depoimento Especial | E48: Promoverem capacitação de magistrados(as) e profissionais que atuem na realização do depoimento especial, inclusive para crianças e adolescentes de povos e comunidades tradicionais, de forma interdisciplinar e continuada, observando os marcos do Protocolo Brasileiro de Entrevista Forense | F48: 20 | G48: =V48 -> 0 | H48: =IFERROR(G48/F48,0) -> 0 | I48: Meales Medeiros de Melo | J48: Antonieta Lucia Maroja Arcoverde Nobrega | K48: ESMA | M48: PLANILHA | N48: 01/08/2025 a 31/07/2026 | O48: 46234 | Q48: 20 | R48: 20 | T48: =IF(D48=B48,CONCATENATE(A48," - ",B48),CONCATENATE(A48," - ",B48," - ",D48)) -> 1. GOVERNANÇA - Capacitação de Magistrados e servidores - Capacitação - Depoimento Especial | U48: =F48 -> 20 | V48: =IFERROR(VLOOKUP(T48,'Parcial - Prestação de contas'!A:D,4, ),0) -> 0
A49: 1. GOVERNANÇA | B49: Capacitação de Magistrados e servidores | C49: 9.XVIII | D49: Capacitação - reflexão e sensibilização de autores de violência doméstica | E49: Capacitação de facilitadores(as) para programas voltados à reflexão e sensibilização de autores de violência doméstica e familiar contra a mulher. | F49: 10 | G49: =V49 -> 0 | H49: =IFERROR(G49/F49,0) -> 0 | I49: Meales Medeiros de Melo | J49: Antonieta Lucia Maroja Arcoverde Nobrega | K49: ESMA | M49: PLANILHA | N49: 01/08/2025 a 31/07/2026 | O49: 46234 | Q49: 10 | R49: 10 | T49: =IF(D49=B49,CONCATENATE(A49," - ",B49),CONCATENATE(A49," - ",B49," - ",D49)) -> 1. GOVERNANÇA - Capacitação de Magistrados e servidores - Capacitação - reflexão e sensibilização de autores de violência doméstica | U49: =F49 -> 10 | V49: =IFERROR(VLOOKUP(T49,'Parcial - Prestação de contas'!A:D,4, ),0) -> 0
A50: 1. GOVERNANÇA | B50: Estruturação de juizados de violência doméstica e familiar | C50: 9.XIX | D50: Estruturação de juizados de violência doméstica e familiar | E50: Criação e instalação ou transformação de unidade judiciária ou nova disponibilização de equipe multidisciplinar ou ampliação do quadro de profissionais especializados de equipe multidisciplinar existente | F50: 20 | G50: =V50 -> 0 | H50: =IFERROR(G50/F50,0) -> 0 | I50: Meales Medeiros de Melo | J50: Leonardo Sousa de Paiva Oliveira | K50: PRESIDÊNCIA | M50: PLANILHA | N50: 01/08/2025 a 31/07/2026 | O50: 46234 | Q50: 20 | R50: 20 | T50: =IF(D50=B50,CONCATENATE(A50," - ",B50),CONCATENATE(A50," - ",B50," - ",D50)) -> 1. GOVERNANÇA - Estruturação de juizados de violência doméstica e familiar | U50: =F50 -> 20 | V50: =IFERROR(VLOOKUP(T50,'Parcial - Prestação de contas'!A:D,4, ),0) -> 0
A51: 1. GOVERNANÇA | B51: Grupos vulnerabilizados - Resolução 497/2023 | C51: 9.XX | D51: Contratação de grupos vulneráveis | E51: 100,00% dos editais de contratação publicados no período de referência com previsão de, no mínimo, 5% de reserva das vagas nos contratos que envolvam prestação de serviços contínuos com regime de dedicação exclusiva de mão de obra | F51: 20 | G51: =V51 -> 0 | H51: =IFERROR(G51/F51,0) -> 0 | I51: Meales Medeiros de Melo | J51: Fabio Jose de Oliveira Araujo | K51: DIADM | M51: PLANILHA | N51: 01/08/2025 a 31/07/2026 | O51: 46234 | Q51: 20 | R51: 10 | T51: =IF(D51=B51,CONCATENATE(A51," - ",B51),CONCATENATE(A51," - ",B51," - ",D51)) -> 1. GOVERNANÇA - Grupos vulnerabilizados - Resolução 497/2023 - Contratação de grupos vulneráveis | U51: =F51 -> 20 | V51: =IFERROR(VLOOKUP(T51,'Parcial - Prestação de contas'!A:D,4, ),0) -> 0
A52: 1. GOVERNANÇA | B52: Aposentadoria | C52: 9.XXI | D52: Programa de Preparação à Aposentadoria (PPA) | E52: Para os tribunais que tiverem instituído o Programa de Preparação à Aposentadoria (PPA) | F52: 10 | G52: =V52 -> 0 | H52: =IFERROR(G52/F52,0) -> 0 | I52: Meales Medeiros de Melo | J52: Silmary Alves de Queiroga Vita | K52: VICE | M52: PLANILHA | N52: SITUAÇÃO EM 31/07/2026 | O52: 46234 | Q52: 10 | R52: 0 | T52: =IF(D52=B52,CONCATENATE(A52," - ",B52),CONCATENATE(A52," - ",B52," - ",D52)) -> 1. GOVERNANÇA - Aposentadoria - Programa de Preparação à Aposentadoria (PPA) | U52: =F52 -> 10 | V52: =IFERROR(VLOOKUP(T52,'Parcial - Prestação de contas'!A:D,4, ),0) -> 0
... A57: 1. GOVERNANÇA | B57: Política Judiciária Nacional para a Primeira Infância | C57: 9.XXV.B | D57: Estruturação de juizados de violência doméstica e familiar | E57: Criação e instalação ou transformação de unidade judiciária ou nova disponibilização de equipe multidisciplinar ou ampliação do quadro de profissionais especializados de equipe multidisciplinar existente | F57: 20 | G57: =V57 -> 0 | H57: =IFERROR(G57/F57,0) -> 0 | I57: Meales Medeiros de Melo | J57: Leonardo Sousa de Paiva Oliveira | K57: PRESIDÊNCIA | M57: PLANILHA | N57: 01/08/2025 a 31/07/2026 | O57: 46234 | Q57: 20 | R57: 20 | T57: =IF(D57=B57,CONCATENATE(A57," - ",B57),CONCATENATE(A57," - ",B57," - ",D57)) -> 1. GOVERNANÇA - Política Judiciária Nacional para a Primeira Infância - Estruturação de juizados de violência doméstica e familiar | U57: =F57 -> 20 | V57: =IFERROR(VLOOKUP(T57,'Parcial - Prestação de contas'!A:D,4, ),0) -> 0
A58: 1. GOVERNANÇA | B58: IPER | C58: 9.XXVI | D58: Índice de Promoção de Equidade Racial | E58: De acordo a pontuação relativa alcançada no Iper × 20 | F58: 20 | G58: =V58 -> 0 | H58: =IFERROR(G58/F58,0) -> 0 | I58: Meales Medeiros de Melo | J58: Jailson Shizue Suassuna | K58: COAPO | M58: SRH E PLANILHA | N58: ANO-BASE 2025 | O58: 46022 | Q58: 12.4 | T58: =IF(D58=B58,CONCATENATE(A58," - ",B58),CONCATENATE(A58," - ",B58," - ",D58)) -> 1. GOVERNANÇA - IPER - Índice de Promoção de Equidade Racial | U58: =F58 -> 20 | V58: =IFERROR(VLOOKUP(T58,'Parcial - Prestação de contas'!A:D,4, ),0) -> 0
A59: 2. PRODUTIVIDADE | B59: Melhores índices no IPC-Jus | C59: 10.I | D59: Melhores índices no IPC-Jus | E59: Resultado do IPC-JUS | F59: 90 | G59: =V59 -> 0 | H59: =IFERROR(G59/F59,0) -> 0 | I59: Alirio Maciel Lima de Brito | J59: Meales Medeiros de Melo | K59: UNIDADES JUDICIÁRIAS | L59: X | M59: PJE E SEEU | N59: ANO-BASE 2025 | O59: 46022 | Q59: 0 | R59: 30 | S59: x | T59: =IF(D59=B59,CONCATENATE(A59," - ",B59),CONCATENATE(A59," - ",B59," - ",D59)) -> 2. PRODUTIVIDADE - Melhores índices no IPC-Jus | U59: =F59 -> 90 | V59: =IFERROR(VLOOKUP(T59,'Parcial - Prestação de contas'!A:D,4, ),0) -> 0
A60: 2. PRODUTIVIDADE | B60: Redução da Taxa de Congestionamento Líquida | C60: 10.II | D60: Taxa de Congestionamento Líquida | E60: Resultado da TCL líquida | F60: 50 | G60: =V60 -> 35 | H60: =IFERROR(G60/F60,0) -> 0.7 | I60: Alirio Maciel Lima de Brito | J60: Meales Medeiros de Melo | K60: UNIDADES JUDICIÁRIAS | L60: X | M60: PJE E SEEU | N60: 01/08/2025 a 31/07/2026 | O60: 46234 | Q60: 0 | R60: 50 | S60: x | T60: =IF(D60=B60,CONCATENATE(A60," - ",B60),CONCATENATE(A60," - ",B60," - ",D60)) -> 2. PRODUTIVIDADE - Redução da Taxa de Congestionamento Líquida - Taxa de Congestionamento Líquida | U60: =F60 -> 50 | V60: =IFERROR(VLOOKUP(T60,'Parcial - Prestação de contas'!A:D,4, ),0) -> 35
A61: 2. PRODUTIVIDADE | B61: Tempo Médio | C61: 10.III | D61: Tempo Médio | E61: A) até 500 dias (50 pontos); B) de 501 a 700 dias (35 pontos); C) de 701 a 900 dias (20 pontos) | F61: 50 | G61: =V61 -> 0 | H61: =IFERROR(G61/F61,0) -> 0 | I61: Alirio Maciel Lima de Brito | J61: Meales Medeiros de Melo | K61: UNIDADES JUDICIÁRIAS | L61: X | M61: PJE E SEEU | N61: SITUAÇÃO EM 31/07/2026 | O61: 46234 | Q61: 35 | R61: 35 | S61: x | T61: =IF(D61=B61,CONCATENATE(A61," - ",B61),CONCATENATE(A61," - ",B61," - ",D61)) -> 2. PRODUTIVIDADE - Tempo Médio | U61: =F61 -> 50 | V61: =IFERROR(VLOOKUP(T61,'Parcial - Prestação de contas'!A:D,4, ),0) -> 0
A62: 2. PRODUTIVIDADE | B62: Índices de Conciliação | C62: 10.IV.A | D62: 1º grau | E62: Indicador I - total de processos com sentenças e decisões terminativas homologatórias de acordo, em relação ao total de processos com sentenças e decisões terminativas, considerando os processos de conhecimento não criminais de primeiro grau | F62: 10 | G62: =V62 -> 0 | H62: =IFERROR(G62/F62,0) -> 0 | I62: Alirio Maciel Lima de Brito | J62: Kleyber Thiago Trovao Eulalio | K62: UNIDADES JUDICIÁRIAS | L62: X | M62: PJE | N62: 01/08/2025 a 31/07/2026 | O62: 46234 | Q62: 10 | R62: 10 | S62: x | T62: =IF(D62=B62,CONCATENATE(A62," - ",B62),CONCATENATE(A62," - ",B62," - ",D62)) -> 2. PRODUTIVIDADE - Índices de Conciliação - 1º grau | U62: =F62 -> 10 | V62: =IFERROR(VLOOKUP(T62,'Parcial - Prestação de contas'!A:D,4, ),0) -> 0
A63: 2. PRODUTIVIDADE | B63: Índices de Conciliação | C63: 10.IV.B | D63: juizados especiais | E63: Indicador II - total de processos com sentenças e decisões terminativas homologatórias de acordo, em relação ao total de processos com sentenças e decisões terminativas, considerando os processos de conhecimento não criminais de juizados especiais | F63: 10 | G63: =V63 -> 0 | H63: =IFERROR(G63/F63,0) -> 0 | I63: Alirio Maciel Lima de Brito | J63: Kleyber Thiago Trovao Eulalio | K63: UNIDADES JUDICIÁRIAS | L63: X | M63: PJE | N63: 01/08/2025 a 31/07/2026 | O63: 46234 | Q63: 0 | S63: x | T63: =IF(D63=B63,CONCATENATE(A63," - ",B63),CONCATENATE(A63," - ",B63," - ",D63)) -> 2. PRODUTIVIDADE - Índices de Conciliação - juizados especiais | U63: =F63 -> 10 | V63: =IFERROR(VLOOKUP(T63,'Parcial - Prestação de contas'!A:D,4, ),0) -> 0
A64: 2. PRODUTIVIDADE | B64: Índices de Conciliação | C64: 10.IV.C | D64: 2º grau | E64: Indicador III - total de processos com sentenças e decisões terminativas homologatórias de acordo, em relação ao total de processos com sentenças e decisões terminativas, considerando os processos de conhecimento não criminais de segundo grau | F64: 10 | G64: =V64 -> 0 | H64: =IFERROR(G64/F64,0) -> 0 | I64: Alirio Maciel Lima de Brito | J64: Kleyber Thiago Trovao Eulalio | K64: UNIDADES JUDICIÁRIAS | L64: X | M64: PJE | N64: 01/08/2025 a 31/07/2026 | O64: 46234 | Q64: 0 | R64: 0 | S64: x | T64: =IF(D64=B64,CONCATENATE(A64," - ",B64),CONCATENATE(A64," - ",B64," - ",D64)) -> 2. PRODUTIVIDADE - Índices de Conciliação - 2º grau | U64: =F64 -> 10 | V64: =IFERROR(VLOOKUP(T64,'Parcial - Prestação de contas'!A:D,4, ),0) -> 0
A65: 2. PRODUTIVIDADE | B65: Índices de Conciliação | C65: 10.IV.D | D65: execução extrajudicial não fiscais | E65: Indicador IV - total de processos com sentenças de execução de títulos executivos extrajudiciais não fiscais homologatórias de acordo, em relação ao total de processos com sentenças de execução de títulos executivos extrajudiciais não fiscais | F65: 10 | G65: =V65 -> 0 | H65: =IFERROR(G65/F65,0) -> 0 | I65: Alirio Maciel Lima de Brito | J65: Kleyber Thiago Trovao Eulalio | K65: UNIDADES JUDICIÁRIAS | L65: X | M65: PJE | N65: 01/08/2025 a 31/07/2026 | O65: 46234 | Q65: 10 | R65: 10 | S65: x | T65: =IF(D65=B65,CONCATENATE(A65," - ",B65),CONCATENATE(A65," - ",B65," - ",D65)) -> 2. PRODUTIVIDADE - Índices de Conciliação - execução extrajudicial não fiscais | U65: =F65 -> 10 | V65: =IFERROR(VLOOKUP(T65,'Parcial - Prestação de contas'!A:D,4, ),0) -> 0
A66: 2. PRODUTIVIDADE | B66: Índices de Conciliação | C66: 10.IV.E. | D66: execução não criminal | E66: Indicador V - total de processos não criminais com sentenças em execução judicial ou em cumprimento de sentença homologatórias de acordo, em relação ao total de processos não criminais com sentenças em execução judicial ou em cumprimento de sentença | F66: 10 | G66: =V66 -> 0 | H66: =IFERROR(G66/F66,0) -> 0 | I66: Alirio Maciel Lima de Brito | J66: Kleyber Thiago Trovao Eulalio | K66: UNIDADES JUDICIÁRIAS | L66: X | M66: PJE | N66: 01/08/2025 a 31/07/2026 | O66: 46234 | Q66: 0 | R66: 0 | S66: x | T66: =IF(D66=B66,CONCATENATE(A66," - ",B66),CONCATENATE(A66," - ",B66," - ",D66)) -> 2. PRODUTIVIDADE - Índices de Conciliação - execução não criminal | U66: =F66 -> 10 | V66: =IFERROR(VLOOKUP(T66,'Parcial - Prestação de contas'!A:D,4, ),0) -> 0
A67: 2. PRODUTIVIDADE | B67: Cumprimento das Metas Nacionais | C67: 10.V.A. | D67: Meta 1 | E67: Meta 1 | F67: 20 | G67: =V67 -> 20 | H67: =IFERROR(G67/F67,0) -> 1 | I67: Alirio Maciel Lima de Brito | J67: Alirio Maciel Lima de Brito | K67: UNIDADES JUDICIÁRIAS | M67: PJE E SEEU | N67: ANO-BASE 2025 | O67: 46022 | Q67: 20 | R67: 20 | S67: x | T67: =IF(D67=B67,CONCATENATE(A67," - ",B67),CONCATENATE(A67," - ",B67," - ",D67)) -> 2. PRODUTIVIDADE - Cumprimento das Metas Nacionais - Meta 1 | U67: =F67 -> 20 | V67: =IFERROR(VLOOKUP(T67,'Parcial - Prestação de contas'!A:D,4, ),0) -> 20
A68: 2. PRODUTIVIDADE | B68: Cumprimento das Metas Nacionais | C68: 10.V.B. | D68: Meta 2 | E68: Meta 2 | F68: 20 | G68: =V68 -> 0 | H68: =IFERROR(G68/F68,0) -> 0 | I68: Alirio Maciel Lima de Brito | J68: Alirio Maciel Lima de Brito | K68: UNIDADES JUDICIÁRIAS | M68: PJE E SEEU | N68: ANO-BASE 2025 | O68: 46022 | Q68: 20 | R68: 20 | S68: x | T68: =IF(D68=B68,CONCATENATE(A68," - ",B68),CONCATENATE(A68," - ",B68," - ",D68)) -> 2. PRODUTIVIDADE - Cumprimento das Metas Nacionais - Meta 2 | U68: =F68 -> 20 | V68: =IFERROR(VLOOKUP(T68,'Parcial - Prestação de contas'!A:D,4, ),0) -> 0
A69: 2. PRODUTIVIDADE | B69: Cumprimento das Metas Nacionais | C69: 10.V.B. | D69: Meta 3 | E69: Meta 3 | F69: 20 | G69: =V69 -> 0 | H69: =IFERROR(G69/F69,0) -> 0 | I69: Alirio Maciel Lima de Brito | J69: Kleyber Thiago Trovao Eulalio | K69: UNIDADES JUDICIÁRIAS | M69: PJE E SEEU | N69: ANO-BASE 2025 | O69: 46022 | Q69: 20 | R69: 10 | S69: x | T69: =IF(D69=B69,CONCATENATE(A69," - ",B69),CONCATENATE(A69," - ",B69," - ",D69)) -> 2. PRODUTIVIDADE - Cumprimento das Metas Nacionais - Meta 3 | U69: =F69 -> 20 | V69: =IFERROR(VLOOKUP(T69,'Parcial - Prestação de contas'!A:D,4, ),0) -> 0
A70: 2. PRODUTIVIDADE | B70: Cumprimento das Metas Nacionais | C70: 10.V.C. | D70: Meta 4 | E70: Meta 4 | F70: 10 | G70: =V70 -> 0 | H70: =IFERROR(G70/F70,0) -> 0 | I70: Alirio Maciel Lima de Brito | J70: Jailson Shizue Suassuna | K70: UNIDADES JUDICIÁRIAS | M70: PJE E SEEU | N70: ANO-BASE 2025 | O70: 46022 | Q70: 10 | R70: 10 | S70: x | T70: =IF(D70=B70,CONCATENATE(A70," - ",B70),CONCATENATE(A70," - ",B70," - ",D70)) -> 2. PRODUTIVIDADE - Cumprimento das Metas Nacionais - Meta 4 | U70: =F70 -> 10 | V70: =IFERROR(VLOOKUP(T70,'Parcial - Prestação de contas'!A:D,4, ),0) -> 0
A71: 2. PRODUTIVIDADE | B71: Cumprimento das Metas Nacionais | C71: 10.V.C. | D71: Meta 5 | E71: Meta 5 | F71: 10 | G71: =V71 -> 0 | H71: =IFERROR(G71/F71,0) -> 0 | I71: Alirio Maciel Lima de Brito | J71: Meales Medeiros de Melo | K71: UNIDADES JUDICIÁRIAS | M71: PJE E SEEU | N71: ANO-BASE 2025 | O71: 46022 | Q71: 10 | R71: 10 | S71: x | T71: =IF(D71=B71,CONCATENATE(A71," - ",B71),CONCATENATE(A71," - ",B71," - ",D71)) -> 2. PRODUTIVIDADE - Cumprimento das Metas Nacionais - Meta 5 | U71: =F71 -> 10 | V71: =IFERROR(VLOOKUP(T71,'Parcial - Prestação de contas'!A:D,4, ),0) -> 0
A72: 2. PRODUTIVIDADE | B72: Cumprimento das Metas Nacionais | C72: 10.V.C. | D72: Meta 6 | E72: Meta 6 | F72: 0 | G72: =V72 -> 0 | H72: =IFERROR(G72/F72,0) -> 0 | I72: Alirio Maciel Lima de Brito | J72: Deborah Cavalcanti Figueiredo | K72: UNIDADES JUDICIÁRIAS | M72: PJE E SEEU | N72: ANO-BASE 2025 | O72: 46022 | S72: x | T72: =IF(D72=B72,CONCATENATE(A72," - ",B72),CONCATENATE(A72," - ",B72," - ",D72)) -> 2. PRODUTIVIDADE - Cumprimento das Metas Nacionais - Meta 6 | U72: =F72 -> 0 | V72: =IFERROR(VLOOKUP(T72,'Parcial - Prestação de contas'!A:D,4, ),0) -> 0
A73: 2. PRODUTIVIDADE | B73: Cumprimento das Metas Nacionais | C73: 10.V.C. | D73: Meta 8 | E73: Meta 8 | F73: 10 | G73: =V73 -> 0 | H73: =IFERROR(G73/F73,0) -> 0 | I73: Alirio Maciel Lima de Brito | J73: Graziela Queiroga Gadelha de Sousa | K73: UNIDADES JUDICIÁRIAS | M73: PJE E SEEU | N73: ANO-BASE 2025 | O73: 46022 | Q73: 10 | R73: 10 | S73: x | T73: =IF(D73=B73,CONCATENATE(A73," - ",B73),CONCATENATE(A73," - ",B73," - ",D73)) -> 2. PRODUTIVIDADE - Cumprimento das Metas Nacionais - Meta 8 | U73: =F73 -> 10 | V73: =IFERROR(VLOOKUP(T73,'Parcial - Prestação de contas'!A:D,4, ),0) -> 0
A74: 2. PRODUTIVIDADE | B74: Cumprimento das Metas Nacionais | C74: 10.V.C. | D74: Meta 10 | E74: Meta 10 | F74: 10 | G74: =V74 -> 0 | H74: =IFERROR(G74/F74,0) -> 0 | I74: Alirio Maciel Lima de Brito | J74: Max Nunes de Franca | K74: UNIDADES JUDICIÁRIAS | M74: PJE E SEEU | N74: ANO-BASE 2025 | O74: 46022 | Q74: 10 | R74: 10 | S74: x | T74: =IF(D74=B74,CONCATENATE(A74," - ",B74),CONCATENATE(A74," - ",B74," - ",D74)) -> 2. PRODUTIVIDADE - Cumprimento das Metas Nacionais - Meta 10 | U74: =F74 -> 10 | V74: =IFERROR(VLOOKUP(T74,'Parcial - Prestação de contas'!A:D,4, ),0) -> 0
A75: 2. PRODUTIVIDADE | B75: Cumprimento das Metas Nacionais | C75: 10.V.C. | D75: Meta 11 | E75: Meta 11 | F75: 10 | G75: =V75 -> 0 | H75: =IFERROR(G75/F75,0) -> 0 | I75: Alirio Maciel Lima de Brito | J75: Maria dos Remedios Pordeus Pedrosa | K75: UNIDADES JUDICIÁRIAS | M75: PJE E SEEU | N75: ANO-BASE 2025 | O75: 46022 | Q75: 5 | R75: 10 | S75: x | T75: =IF(D75=B75,CONCATENATE(A75," - ",B75),CONCATENATE(A75," - ",B75," - ",D75)) -> 2. PRODUTIVIDADE - Cumprimento das Metas Nacionais - Meta 11 | U75: =F75 -> 10 | V75: =IFERROR(VLOOKUP(T75,'Parcial - Prestação de contas'!A:D,4, ),0) -> 0
A76: 2. PRODUTIVIDADE | B76: Cumprimento das Metas Nacionais | C76: 10.V.D. | D76: Meta 9 | E76: Meta 9 | F76: 10 | G76: =V76 -> 0 | H76: =IFERROR(G76/F76,0) -> 0 | I76: Alirio Maciel Lima de Brito | J76: Natan Figueredo Oliveira | K76: COINO | M76: PLANILHA | N76: ANO-BASE 2025 | O76: 46022 | Q76: 10 | R76: 0 | T76: =IF(D76=B76,CONCATENATE(A76," - ",B76),CONCATENATE(A76," - ",B76," - ",D76)) -> 2. PRODUTIVIDADE - Cumprimento das Metas Nacionais - Meta 9 | U76: =F76 -> 10 | V76: =IFERROR(VLOOKUP(T76,'Parcial - Prestação de contas'!A:D,4, ),0) -> 0
A77: 2. PRODUTIVIDADE | B77: Julgar processos antigos | C77: 10.VI | D77: Julgar processos antigos | E77: Ajuizados até o ano de 2022 dos casos pendentes líquidos e não julgados até 31/7/2025 A) até 20,00% (50 pontos); B) de 20,01% a 25,00% (25 pontos). | F77: 50 | G77: =V77 -> 0 | H77: =IFERROR(G77/F77,0) -> 0 | I77: Alirio Maciel Lima de Brito | J77: Meales Medeiros de Melo | K77: UNIDADES JUDICIÁRIAS | L77: X | M77: PJE E SEEU | N77: SITUAÇÃO EM 31/07/2026 | O77: 46234 | Q77: 50 | R77: 25 | S77: x | T77: =IF(D77=B77,CONCATENATE(A77," - ",B77),CONCATENATE(A77," - ",B77," - ",D77)) -> 2. PRODUTIVIDADE - Julgar processos antigos | U77: =F77 -> 50 | V77: =IFERROR(VLOOKUP(T77,'Parcial - Prestação de contas'!A:D,4, ),0) -> 0
A78: 2. PRODUTIVIDADE | B78: Julgar Violência contra a Mulher | C78: 10.VII.A | D78: Tempo Médio - Feminicídio | E78: Tempo médio decorrido entre a data do início da ação penal e a data-base de cálculo nos processos de violência doméstica e familiar contra a mulher pendentes líquidos | F78: 20 | G78: =V78 -> 0 | H78: =IFERROR(G78/F78,0) -> 0 | I78: Alirio Maciel Lima de Brito | J78: Graziela Queiroga Gadelha de Sousa | K78: UNIDADES JUDICIÁRIAS | L78: X | M78: PJE | N78: SITUAÇÃO EM 31/07/2026 | O78: 46234 | Q78: 20 | R78: 10 | S78: x | T78: =IF(D78=B78,CONCATENATE(A78," - ",B78),CONCATENATE(A78," - ",B78," - ",D78)) -> 2. PRODUTIVIDADE - Julgar Violência contra a Mulher - Tempo Médio - Feminicídio | U78: =F78 -> 20 | V78: =IFERROR(VLOOKUP(T78,'Parcial - Prestação de contas'!A:D,4, ),0) -> 0
A79: 2. PRODUTIVIDADE | B79: Julgar Violência contra a Mulher | C79: 10.VII.B | D79: Tempo médio - VD | E79: Tempo médio decorrido entre a data do início da ação penal e a data-base de cálculo nos processos de feminicídio pendentes líquidos | F79: 20 | G79: =V79 -> 0 | H79: =IFERROR(G79/F79,0) -> 0 | I79: Alirio Maciel Lima de Brito | J79: Graziela Queiroga Gadelha de Sousa | K79: UNIDADES JUDICIÁRIAS | L79: X | M79: PJE | N79: SITUAÇÃO EM 31/07/2026 | O79: 46234 | Q79: 10 | R79: 0 | S79: x | T79: =IF(D79=B79,CONCATENATE(A79," - ",B79),CONCATENATE(A79," - ",B79," - ",D79)) -> 2. PRODUTIVIDADE - Julgar Violência contra a Mulher - Tempo médio - VD | U79: =F79 -> 20 | V79: =IFERROR(VLOOKUP(T79,'Parcial - Prestação de contas'!A:D,4, ),0) -> 0
A80: 2. PRODUTIVIDADE | B80: Julgar Violência contra a Mulher | C80: 10.VII.C | D80: Tempo Médio - Medida Protetiva | E80: Tempo médio decorrido entre a data do recebimento/ajuizamento e a data da primeira concessão ou denegação da medida protetiva, nos processos de violência doméstica e familiar contra a mulher, das classes de medidas protetivas de urgência, de até 2 dias | F80: 20 | G80: =V80 -> 0 | H80: =IFERROR(G80/F80,0) -> 0 | I80: Alirio Maciel Lima de Brito | J80: Graziela Queiroga Gadelha de Sousa | K80: UNIDADES JUDICIÁRIAS | L80: X | M80: PJE | N80: 01/08/2025 a 31/07/2026 | O80: 46234 | Q80: 20 | R80: 20 | S80: x | T80: =IF(D80=B80,CONCATENATE(A80," - ",B80),CONCATENATE(A80," - ",B80," - ",D80)) -> 2. PRODUTIVIDADE - Julgar Violência contra a Mulher - Tempo Médio - Medida Protetiva | U80: =F80 -> 20 | V80: =IFERROR(VLOOKUP(T80,'Parcial - Prestação de contas'!A:D,4, ),0) -> 0
A81: 2. PRODUTIVIDADE | B81: Judicialização da Saúde | C81: 10.VIII. | D81: Tempo Médio | E81: Tempo médio decorrido entre a data do início da ação e a data-base de cálculo nos processos de judicialização da saúde pendentes líquidos | F81: 20 | G81: =V81 -> 0 | H81: =IFERROR(G81/F81,0) -> 0 | I81: Alirio Maciel Lima de Brito | J81: Silmary Alves de Queiroga Vita | K81: UNIDADES JUDICIÁRIAS | L81: X | M81: PJE | N81: SITUAÇÃO EM 31/07/2026 | O81: 46234 | Q81: 10 | R81: 10 | S81: x | T81: =IF(D81=B81,CONCATENATE(A81," - ",B81),CONCATENATE(A81," - ",B81," - ",D81)) -> 2. PRODUTIVIDADE - Judicialização da Saúde - Tempo Médio | U81: =F81 -> 20 | V81: =IFERROR(VLOOKUP(T81,'Parcial - Prestação de contas'!A:D,4, ),0) -> 0
A82: 2. PRODUTIVIDADE | B82: Adoção e acolhimento | C82: 10.X.A. | D82: Reavaliação de acolhimento | E82: Reavaliação de acolhimento | F82: 20 | G82: =V82 -> 0 | H82: =IFERROR(G82/F82,0) -> 0 | I82: Alirio Maciel Lima de Brito | J82: Fabio Leandro de Alencar Cunha | K82: CEJA/UNIDADES JUDICIÁRIAS | L82: X | M82: SNA | N82: 30/04/2026 a 31/07/2026 | O82: 46234 | Q82: 0 | R82: 10 | S82: x | T82: =IF(D82=B82,CONCATENATE(A82," - ",B82),CONCATENATE(A82," - ",B82," - ",D82)) -> 2. PRODUTIVIDADE - Adoção e acolhimento - Reavaliação de acolhimento | U82: =F82 -> 20 | V82: =IFERROR(VLOOKUP(T82,'Parcial - Prestação de contas'!A:D,4, ),0) -> 0
A83: 2. PRODUTIVIDADE | B83: Adoção e acolhimento | C83: 10.X.B.B1. | D83: Tempo Médio - Adoção | E83: Acima de 80,00% dos processos de adoção pelo cadastro do SNA que tramitam há 240 dias ou menos | F83: 10 | G83: =V83 -> 0 | H83: =IFERROR(G83/F83,0) -> 0 | I83: Alirio Maciel Lima de Brito | J83: Fabio Leandro de Alencar Cunha | K83: CEJA/UNIDADES JUDICIÁRIAS | L83: X | M83: SNA | N83: SITUAÇÃO EM 31/07/2026 | O83: 46234 | Q83: 0 | R83: 10 | S83: x | T83: =IF(D83=B83,CONCATENATE(A83," - ",B83),CONCATENATE(A83," - ",B83," - ",D83)) -> 2. PRODUTIVIDADE - Adoção e acolhimento - Tempo Médio - Adoção | U83: =F83 -> 10 | V83: =IFERROR(VLOOKUP(T83,'Parcial - Prestação de contas'!A:D,4, ),0) -> 0
A84: 2. PRODUTIVIDADE | B84: Adoção e acolhimento | C84: 10.X.B.B2. | D84: Tempo Médio - Destituição do poder familiar | E84: Acima de 80,00% dos processos de destituição do poder familiar no SNA que tramitam há 120 dias ou menos | F84: 10 | G84: =V84 -> 0 | H84: =IFERROR(G84/F84,0) -> 0 | I84: Alirio Maciel Lima de Brito | J84: Fabio Leandro de Alencar Cunha | K84: CEJA/UNIDADES JUDICIÁRIAS | L84: X | M84: SNA | N84: SITUAÇÃO EM 31/07/2026 | O84: 46234 | Q84: 0 | R84: 0 | S84: x | T84: =IF(D84=B84,CONCATENATE(A84," - ",B84),CONCATENATE(A84," - ",B84," - ",D84)) -> 2. PRODUTIVIDADE - Adoção e acolhimento - Tempo Médio - Destituição do poder familiar | U84: =F84 -> 10 | V84: =IFERROR(VLOOKUP(T84,'Parcial - Prestação de contas'!A:D,4, ),0) -> 0
A85: 2. PRODUTIVIDADE | B85: Adoção e acolhimento | C85: 10.X.C. | D85: CPF cadastrado das crianças acolhidas | E85: Acima de 90,00% das crianças e dos(as) adolescentes acolhidos(as) há mais de 30 dias que tenham o CPF cadastrado | F85: 20 | G85: =V85 -> 0 | H85: =IFERROR(G85/F85,0) -> 0 | I85: Alirio Maciel Lima de Brito | J85: Fabio Leandro de Alencar Cunha | K85: CEJA/UNIDADES JUDICIÁRIAS | L85: X | M85: SNA | N85: INICIADOS ATÉ 30/06/2026 E ATIVOS ATÉ 31/07/2026 | O85: 46234 | Q85: 20 | R85: 20 | S85: x | T85: =IF(D85=B85,CONCATENATE(A85," - ",B85),CONCATENATE(A85," - ",B85," - ",D85)) -> 2. PRODUTIVIDADE - Adoção e acolhimento - CPF cadastrado das crianças acolhidas | U85: =F85 -> 20 | V85: =IFERROR(VLOOKUP(T85,'Parcial - Prestação de contas'!A:D,4, ),0) -> 0
A86: 2. PRODUTIVIDADE | B86: Ações Penais (geral e júri) | C86: 10.XI.A. | D86: Tempo Médio Ação Penal | E86: Tempo médio dos processos pendentes líquidos, considerando o número de dias decorridos entre o início da ação penal e a data-base de cálculo | F86: 20 | G86: =V86 -> 0 | H86: =IFERROR(G86/F86,0) -> 0 | I86: Alirio Maciel Lima de Brito | J86: Marcial Henrique Ferraz da Cruz | K86: UNIDADES JUDICIÁRIAS | M86: PJE | N86: SITUAÇÃO EM 31/07/2026 | O86: 46234 | Q86: 10 | R86: 0 | S86: x | T86: =IF(D86=B86,CONCATENATE(A86," - ",B86),CONCATENATE(A86," - ",B86," - ",D86)) -> 2. PRODUTIVIDADE - Ações Penais (geral e júri) - Tempo Médio Ação Penal | U86: =F86 -> 20 | V86: =IFERROR(VLOOKUP(T86,'Parcial - Prestação de contas'!A:D,4, ),0) -> 0
A87: 2. PRODUTIVIDADE | B87: Ações Penais (geral e júri) | C87: 10.XI.B. | D87: Tempo Médio Ação do Júri | E87: Tempo médio dos processos pendentes líquidos, decorrido entre a data do início da ação penal de competência do júri e data-base de cálculo | F87: 20 | G87: =V87 -> 0 | H87: =IFERROR(G87/F87,0) -> 0 | I87: Alirio Maciel Lima de Brito | J87: Marcial Henrique Ferraz da Cruz | K87: UNIDADES JUDICIÁRIAS | M87: PJE | N87: SITUAÇÃO EM 31/07/2026 | O87: 46234 | Q87: 10 | R87: 0 | S87: x | T87: =IF(D87=B87,CONCATENATE(A87," - ",B87),CONCATENATE(A87," - ",B87," - ",D87)) -> 2. PRODUTIVIDADE - Ações Penais (geral e júri) - Tempo Médio Ação do Júri | U87: =F87 -> 20 | V87: =IFERROR(VLOOKUP(T87,'Parcial - Prestação de contas'!A:D,4, ),0) -> 0
A88: 2. PRODUTIVIDADE | B88: Julgar IRDR ou IAC | C88: 10.XII. | D88: Julgar IRDR ou IAC | E88: para cada IRDR ou para cada IAC julgado no período de referência | F88: 15 | G88: =V88 -> 0 | H88: =IFERROR(G88/F88,0) -> 0 | I88: Alirio Maciel Lima de Brito | J88: Frederico Martinho da Nobrega Coutinho | K88: GABINETES | N88: 01/08/2025 a 31/07/2026 | O88: 46234 | Q88: 0 | R88: 10 | T88: =IF(D88=B88,CONCATENATE(A88," - ",B88),CONCATENATE(A88," - ",B88," - ",D88)) -> 2. PRODUTIVIDADE - Julgar IRDR ou IAC | U88: =F88 -> 15 | V88: =IFERROR(VLOOKUP(T88,'Parcial - Prestação de contas'!A:D,4, ),0) -> 0
A89: 2. PRODUTIVIDADE | B89: Unidades judiciárias com IAD acima de 100% | C89: 10.XIII.A. | D89: 1º Grau | E89: Percentual de unidades judiciárias de primeiro grau com IAD igual ou maior que 100,00% | F89: 30 | G89: =V89 -> 0 | H89: =IFERROR(G89/F89,0) -> 0 | I89: Alirio Maciel Lima de Brito | J89: Meales Medeiros de Melo | K89: UNIDADES JUDICIÁRIAS | M89: PJE | N89: 01/08/2025 a 31/07/2026 | O89: 46234 | Q89: 15 | R89: 16 | S89: x | T89: =IF(D89=B89,CONCATENATE(A89," - ",B89),CONCATENATE(A89," - ",B89," - ",D89)) -> 2. PRODUTIVIDADE - Unidades judiciárias com IAD acima de 100% - 1º Grau | U89: =F89 -> 30 | V89: =IFERROR(VLOOKUP(T89,'Parcial - Prestação de contas'!A:D,4, ),0) -> 0
A90: 2. PRODUTIVIDADE | B90: Unidades judiciárias com IAD acima de 100% | C90: 10.XIII.B. | D90: 2º Grau | E90: Percentual de unidades judiciárias de segundo grau ou em unidades de tribunais Superiores, com IAD igual ou maior que 100,00% | F90: 20 | G90: =V90 -> 0 | H90: =IFERROR(G90/F90,0) -> 0 | I90: Alirio Maciel Lima de Brito | J90: Meales Medeiros de Melo | K90: UNIDADES JUDICIÁRIAS | M90: PJE | N90: 01/08/2025 a 31/07/2026 | O90: 46234 | Q90: 15 | R90: 15 | S90: x | T90: =IF(D90=B90,CONCATENATE(A90," - ",B90),CONCATENATE(A90," - ",B90," - ",D90)) -> 2. PRODUTIVIDADE - Unidades judiciárias com IAD acima de 100% - 2º Grau | U90: =F90 -> 20 | V90: =IFERROR(VLOOKUP(T90,'Parcial - Prestação de contas'!A:D,4, ),0) -> 0
A91: 2. PRODUTIVIDADE | B91: Juízo Verde | C91: 10.XIV.A | D91: IAD | E91: IAD nas ações ambientais igual ou maior que 100,00% | F91: 20 | G91: =V91 -> 0 | H91: =IFERROR(G91/F91,0) -> 0 | I91: Alirio Maciel Lima de Brito | J91: Deborah Cavalcanti Figueiredo | K91: UNIDADES JUDICIÁRIAS | L91: x | M91: PJE | N91: 01/08/2025 a 31/07/2026 | O91: 46234 | Q91: 0 | R91: 0 | S91: x | T91: =IF(D91=B91,CONCATENATE(A91," - ",B91),CONCATENATE(A91," - ",B91," - ",D91)) -> 2. PRODUTIVIDADE - Juízo Verde - IAD | U91: =F91 -> 20 | V91: =IFERROR(VLOOKUP(T91,'Parcial - Prestação de contas'!A:D,4, ),0) -> 0
A92: 2. PRODUTIVIDADE | B92: Juízo Verde | C92: 10.XIV.B | D92: Julgamento dos processos antigos | E92: Julgar, entre 1º/8/2024 e 31/7/2025, pelo menos 35,00% dos processos ambientais ingressados até 31/12/2021 e que não tinham sido julgados ou baixados até 31/7/2024. Excluem-se os processos pendentes que estavam suspensos, sobrestados ou em arquivo provisório em 31/7/2024 | F92: 20 | G92: =V92 -> 0 | H92: =IFERROR(G92/F92,0) -> 0 | I92: Alirio Maciel Lima de Brito | J92: Deborah Cavalcanti Figueiredo | K92: UNIDADES JUDICIÁRIAS | L92: x | M92: PJE | N92: 01/08/2025 a 31/07/2026 | O92: 46234 | Q92: 20 | R92: 20 | S92: x | T92: =IF(D92=B92,CONCATENATE(A92," - ",B92),CONCATENATE(A92," - ",B92," - ",D92)) -> 2. PRODUTIVIDADE - Juízo Verde - Julgamento dos processos antigos | U92: =F92 -> 20 | V92: =IFERROR(VLOOKUP(T92,'Parcial - Prestação de contas'!A:D,4, ),0) -> 0
A93: 2. PRODUTIVIDADE | B93: Incidentes de progressão de regime | C93: 10.XV | D93: Incidentes de progressão de regime | E93: Média do resultado alcançado por cada unidade judiciária em cada mês-base, no que diz respeito à proporção entre a soma de incidentes de progressão de regime vencidos no SEEU e a soma do número de processos ativos na respectiva unidade judiciária e mês-base de medição.Os cálculos serão efetuados no 15° dia útil subsequente ao mês-base. | F93: 60 | G93: =V93 -> 0 | H93: =IFERROR(G93/F93,0) -> 0 | I93: Alirio Maciel Lima de Brito | J93: Andrea Arcoverde Cavalcanti Vaz | K93: UNIDADES JUDICIÁRIAS | L93: x | M93: SEEU | N93: 01/08/2025 a 31/07/2026 | O93: 46234 | R93: -30 | S93: x | T93: =IF(D93=B93,CONCATENATE(A93," - ",B93),CONCATENATE(A93," - ",B93," - ",D93)) -> 2. PRODUTIVIDADE - Incidentes de progressão de regime | U93: =F93 -> 60 | V93: =IFERROR(VLOOKUP(T93,'Parcial - Prestação de contas'!A:D,4, ),0) -> 0
A94: 2. PRODUTIVIDADE | B94: Audiências concentradas socioeducativo | C94: 10.XVI.A | D94: Regulamentação | E94: Regulamentação das audiências concentradas para reavaliação de medidas socioeducativas de internação e semiliberdade | F94: 5 | G94: =V94 -> 0 | H94: =IFERROR(G94/F94,0) -> 0 | I94: Alirio Maciel Lima de Brito | J94: Maria dos Remedios Pordeus Pedrosa | K94: UNIDADES JUDICIÁRIAS | L94: x | M94: PJE | N94: SITUAÇÃO EM 31/07/2026 | O94: 46234 | Q94: 5 | S94: x | T94: =IF(D94=B94,CONCATENATE(A94," - ",B94),CONCATENATE(A94," - ",B94," - ",D94)) -> 2. PRODUTIVIDADE - Audiências concentradas socioeducativo - Regulamentação | U94: =F94 -> 5 | V94: =IFERROR(VLOOKUP(T94,'Parcial - Prestação de contas'!A:D,4, ),0) -> 0
A95: 2. PRODUTIVIDADE | B95: Audiências concentradas socioeducativo | C95: 10.XVI.B | D95: Audiências concentradas socioeducativo | E95: Realização de audiências concentradas de reavaliação de medidas socioeducativas de internação e semiliberdade | F95: 15 | G95: =V95 -> 0 | H95: =IFERROR(G95/F95,0) -> 0 | I95: Alirio Maciel Lima de Brito | J95: Maria dos Remedios Pordeus Pedrosa | K95: UNIDADES JUDICIÁRIAS | L95: x | M95: PJE | N95: 01/08/2025 a 31/07/2026 | O95: 46234 | Q95: 15 | S95: x | T95: =IF(D95=B95,CONCATENATE(A95," - ",B95),CONCATENATE(A95," - ",B95," - ",D95)) -> 2. PRODUTIVIDADE - Audiências concentradas socioeducativo | U95: =F95 -> 15 | V95: =IFERROR(VLOOKUP(T95,'Parcial - Prestação de contas'!A:D,4, ),0) -> 0
A96: 2. PRODUTIVIDADE | B96: Julgamento apurações infracionais | C96: 10.XVII.A | D96: Tempo médio | E96: Tempo médio dos processos pendentes líquidos, considerando o número de dias decorridos entre o início da representação do ato infracional e a data-base de cálculo | F96: 20 | G96: =V96 -> 0 | H96: =IFERROR(G96/F96,0) -> 0 | I96: Alirio Maciel Lima de Brito | J96: Maria dos Remedios Pordeus Pedrosa | K96: UNIDADES JUDICIÁRIAS | L96: x | M96: PJE | N96: SITUAÇÃO EM 31/07/2026 | O96: 46234 | Q96: 0 | S96: x | T96: =IF(D96=B96,CONCATENATE(A96," - ",B96),CONCATENATE(A96," - ",B96," - ",D96)) -> 2. PRODUTIVIDADE - Julgamento apurações infracionais - Tempo médio | U96: =F96 -> 20 | V96: =IFERROR(VLOOKUP(T96,'Parcial - Prestação de contas'!A:D,4, ),0) -> 0
A97: 4. DADOS E TECNOLOGIA | B97: DataJud | C97: 12.I.A.A1 | D97: Assunto válido | E97: Mais de 98,00% dos processos com tipoAssuntoProcessual.codigoNacional e/ou tipoAssuntoLocal.codigoPaiNacional válidos que sejam folha (último nível) ou de nível 3 ou mais | F97: 10 | G97: =V97 -> 0 | H97: =IFERROR(G97/F97,0) -> 0 | I97: Anderley Ferreira Marques | J97: Paula Frassinetti V. de Andrade | K97: GEPJE | L97: x | M97: PJE | N97: SITUAÇÃO EM 31/07/2026 | O97: 46234 | Q97: 10 | R97: 0 | T97: =IF(D97=B97,CONCATENATE(A97," - ",B97),CONCATENATE(A97," - ",B97," - ",D97)) -> 4. DADOS E TECNOLOGIA - DataJud - Assunto válido | U97: =F97 -> 10 | V97: =IFERROR(VLOOKUP(T97,'Parcial - Prestação de contas'!A:D,4, ),0) -> 0
A98: 4. DADOS E TECNOLOGIA | B98: DataJud | C98: 12.I.A.A2 | D98: Movimento válido | E98: Mais de 95,00% dos processos com tipoMovimentoNacional.codigoNacional e/ou tipoMovimentoLocal.codigoPaiNacional preenchidos, válidos e em último nível | F98: 10 | G98: =V98 -> 0 | H98: =IFERROR(G98/F98,0) -> 0 | I98: Anderley Ferreira Marques | J98: Paula Frassinetti V. de Andrade | K98: GEPJE | L98: x | M98: PJE | N98: SITUAÇÃO EM 31/07/2026 | O98: 46234 | Q98: 10 | R98: 10 | T98: =IF(D98=B98,CONCATENATE(A98," - ",B98),CONCATENATE(A98," - ",B98," - ",D98)) -> 4. DADOS E TECNOLOGIA - DataJud - Movimento válido | U98: =F98 -> 10 | V98: =IFERROR(VLOOKUP(T98,'Parcial - Prestação de contas'!A:D,4, ),0) -> 0
A99: 4. DADOS E TECNOLOGIA | B99: DataJud | C99: 12.I.A.A3 | D99: Movimento com complemento | E99: Mais de 90,00% dos movimentos que possuam complementos tabelados com os campos movimentoNacional.complemento e/ou movimentoLocal.complemento preenchidos e em formato válido, no padrão do modelo XSD | F99: 10 | G99: =V99 -> 0 | H99: =IFERROR(G99/F99,0) -> 0 | I99: Anderley Ferreira Marques | J99: Paula Frassinetti V. de Andrade | K99: GEPJE | L99: x | M99: PJE | N99: SITUAÇÃO EM 31/07/2026 | O99: 46234 | Q99: 10 | R99: 10 | T99: =IF(D99=B99,CONCATENATE(A99," - ",B99),CONCATENATE(A99," - ",B99," - ",D99)) -> 4. DADOS E TECNOLOGIA - DataJud - Movimento com complemento | U99: =F99 -> 10 | V99: =IFERROR(VLOOKUP(T99,'Parcial - Prestação de contas'!A:D,4, ),0) -> 0
A100: 4. DADOS E TECNOLOGIA | B100: DataJud | C100: 12.I.B.B1 | D100: Documento do Polo ativo | E100: Mais de 95,00% dos processos Pessoa.numeroDocumentoPrincipal preenchidos e em formato válido, em pessoa do polo ativo E PoloProcessual.polo, tipo igual AT: polo ativo preenchido | F100: 10 | G100: =V100 -> 0 | H100: =IFERROR(G100/F100,0) -> 0 | I100: Anderley Ferreira Marques | J100: Paula Frassinetti V. de Andrade | K100: GEPJE | L100: x | M100: PJE | N100: SITUAÇÃO EM 31/07/2026 | O100: 46234 | Q100: 10 | R100: 10 | T100: =IF(D100=B100,CONCATENATE(A100," - ",B100),CONCATENATE(A100," - ",B100," - ",D100)) -> 4. DADOS E TECNOLOGIA - DataJud - Documento do Polo ativo | U100: =F100 -> 10 | V100: =IFERROR(VLOOKUP(T100,'Parcial - Prestação de contas'!A:D,4, ),0) -> 0
A101: 4. DADOS E TECNOLOGIA | B101: DataJud | C101: 12.I.B.B2 | D101: Documento do Polo passivo | E101: Mais de 95,00% dos processos Pessoa.numeroDocumentoPrincipal preenchidos e em formato válido, em pessoa do polo passivo PoloProcessual.polo, tipo igual PA: polo passivo preenchido | F101: 10 | G101: =V101 -> 0 | H101: =IFERROR(G101/F101,0) -> 0 | I101: Anderley Ferreira Marques | J101: Paula Frassinetti V. de Andrade | K101: GEPJE | L101: x | M101: PJE | N101: SITUAÇÃO EM 31/07/2026 | O101: 46234 | Q101: 0 | R101: 10 | T101: =IF(D101=B101,CONCATENATE(A101," - ",B101),CONCATENATE(A101," - ",B101," - ",D101)) -> 4. DADOS E TECNOLOGIA - DataJud - Documento do Polo passivo | U101: =F101 -> 10 | V101: =IFERROR(VLOOKUP(T101,'Parcial - Prestação de contas'!A:D,4, ),0) -> 0
A102: 4. DADOS E TECNOLOGIA | B102: DataJud | C102: 12.I.B.B3 | D102: Processos Advogado polo passivo | E102: Mais de 90,00% dos processos advogado.tipoRepresentante, dos tipos tipoRepresentanteProcessual e modalidadeRepresentanteProcessual, preenchidos e enviados no polo passivo e no polo passivo, com uma das opções válidas (“A” para advogado, “E” para escritório de advocacia, “M” para ministério público, “D” para defensoria pública e “P” para outros órgãos | F102: 10 | G102: =V102 -> 0 | H102: =IFERROR(G102/F102,0) -> 0 | I102: Anderley Ferreira Marques | J102: Paula Frassinetti V. de Andrade | K102: GEPJE | L102: x | M102: PJE | N102: SITUAÇÃO EM 31/07/2026 | O102: 46234 | Q102: 0 | R102: 0 | T102: =IF(D102=B102,CONCATENATE(A102," - ",B102),CONCATENATE(A102," - ",B102," - ",D102)) -> 4. DADOS E TECNOLOGIA - DataJud - Processos Advogado polo passivo | U102: =F102 -> 10 | V102: =IFERROR(VLOOKUP(T102,'Parcial - Prestação de contas'!A:D,4, ),0) -> 0
A103: 4. DADOS E TECNOLOGIA | B103: DataJud | C103: 12.I.B.B4 | D103: Processo Advogado - representante | E103: Mais de 90,00% dos processos advogado.inscricao de número de inscrição da OAB, dos tipos tipoRepresentanteProcessual e tipoCadastroOAB, preenchidos para os tipoRepresentante=”A” (advogado) | F103: 10 | G103: =V103 -> 0 | H103: =IFERROR(G103/F103,0) -> 0 | I103: Anderley Ferreira Marques | J103: Paula Frassinetti V. de Andrade | K103: GEPJE | L103: x | M103: PJE | N103: SITUAÇÃO EM 31/07/2026 | O103: 46234 | Q103: 10 | R103: 5 | T103: =IF(D103=B103,CONCATENATE(A103," - ",B103),CONCATENATE(A103," - ",B103," - ",D103)) -> 4. DADOS E TECNOLOGIA - DataJud - Processo Advogado - representante | U103: =F103 -> 10 | V103: =IFERROR(VLOOKUP(T103,'Parcial - Prestação de contas'!A:D,4, ),0) -> 0
A104: 4. DADOS E TECNOLOGIA | B104: DataJud | C104: 12.I.C.C1 | D104: Movimento de audiência com complemento | E104: mais de 95,00% dos movimentos de audiência (970 ou filhos) com complemento preenchido em formato válido | F104: 10 | G104: =V104 -> 0 | H104: =IFERROR(G104/F104,0) -> 0 | I104: Anderley Ferreira Marques | J104: Paula Frassinetti V. de Andrade | K104: GEPJE | L104: x | M104: PJE | N104: SITUAÇÃO EM 31/07/2026 | O104: 46234 | Q104: 10 | R104: 5 | T104: =IF(D104=B104,CONCATENATE(A104," - ",B104),CONCATENATE(A104," - ",B104," - ",D104)) -> 4. DADOS E TECNOLOGIA - DataJud - Movimento de audiência com complemento | U104: =F104 -> 10 | V104: =IFERROR(VLOOKUP(T104,'Parcial - Prestação de contas'!A:D,4, ),0) -> 0
...

Sheet Parcial - Prestação de contas
A1: COLAR AQUI | D1: PONTOS ESTIMADOS
A2: 2. PRODUTIVIDADE - Cumprimento das Metas Nacionais - Meta 1 | B2: CUMPRIDO OU EM CUMPRIMENTO | C2: Não se aplica | D2: =IF(B2="PARCIALMENTE CUMPRIDO",C2,IF(B2="NÃO CUMPRIDO",0,VLOOKUP(A2,BD!T:U,2,))) -> 20
A3: 2. PRODUTIVIDADE - Incidentes de progressão de regime | B3: NÃO CUMPRIDO | C3: Não se aplica | D3: =IF(B3="PARCIALMENTE CUMPRIDO",C3,IF(B3="NÃO CUMPRIDO",0,VLOOKUP(A3,BD!T:U,2,))) -> 0
A4: 2. PRODUTIVIDADE - Redução da Taxa de Congestionamento Líquida - Taxa de Congestionamento Líquida | B4: PARCIALMENTE CUMPRIDO | C4: 35 | D4: =IF(B4="PARCIALMENTE CUMPRIDO",C4,IF(B4="NÃO CUMPRIDO",0,VLOOKUP(A4,BD!T:U,2,))) -> 35

Sheet Juizes
A1: Pedro Davi Alves de Vasconcelos
A2: Jeremias de Cassio Carneiro de Melo
A3: Meales Medeiros de Melo
A4: Anderley Ferreira Marques
A5: Alirio Maciel Lima de Brito
A6: Max Nunes de Franca
A7: Maria Aparecida Sarmento Gadelha
A8: Andrea Arcoverde Cavalcanti Vaz
A9: Silmary Alves de Queiroga Vita
A10: Leonardo Sousa de Paiva Oliveira
A11: Jailson Shizue Suassuna
A12: Graziela Queiroga Gadelha de Sousa
... A31: Paula Frassinetti V. de Andrade
